{
"meta":{"test_sets":[],"test_metrics":[],"learn_metrics":[{"best_value":"Min","name":"RMSE"}],"launch_mode":"Train","parameters":"","iteration_count":1000,"learn_sets":["learn"],"name":"experiment"},
"iterations":[
{"learn":[14.59871775],"iteration":0,"passed_time":0.05939843664,"remaining_time":59.3390382},
{"learn":[14.22518863],"iteration":1,"passed_time":0.05967123376,"remaining_time":29.77594564},
{"learn":[13.8866124],"iteration":2,"passed_time":0.05996078121,"remaining_time":19.92696629},
{"learn":[13.52356875],"iteration":3,"passed_time":0.06023895343,"remaining_time":14.9994994},
{"learn":[13.18870211],"iteration":4,"passed_time":0.06050529209,"remaining_time":12.04055312},
{"learn":[12.9124226],"iteration":5,"passed_time":0.06079513121,"remaining_time":10.07172674},
{"learn":[12.60003351],"iteration":6,"passed_time":0.0610734701,"remaining_time":8.663707973},
{"learn":[12.32990573],"iteration":7,"passed_time":0.06133064191,"remaining_time":7.604999596},
{"learn":[12.0660619],"iteration":8,"passed_time":0.06159389717,"remaining_time":6.782172455},
{"learn":[11.77309809],"iteration":9,"passed_time":0.06185419403,"remaining_time":6.123565209},
{"learn":[11.49227636],"iteration":10,"passed_time":0.06210386569,"remaining_time":5.583702106},
{"learn":[11.26264833],"iteration":11,"passed_time":0.06235549571,"remaining_time":5.133935814},
{"learn":[11.04260393],"iteration":12,"passed_time":0.06264258478,"remaining_time":4.756017783},
{"learn":[10.79916926],"iteration":13,"passed_time":0.06296596624,"remaining_time":4.434603051},
{"learn":[10.5541002],"iteration":14,"passed_time":0.06322284638,"remaining_time":4.151633579},
{"learn":[10.31918115],"iteration":15,"passed_time":0.06347230969,"remaining_time":3.903547046},
{"learn":[10.10004441],"iteration":16,"passed_time":0.06374252342,"remaining_time":3.685817678},
{"learn":[9.894556723],"iteration":17,"passed_time":0.06401190381,"remaining_time":3.492204974},
{"learn":[9.690174082],"iteration":18,"passed_time":0.0642569087,"remaining_time":3.317685654},
{"learn":[9.506034866],"iteration":19,"passed_time":0.06449274675,"remaining_time":3.160144591},
{"learn":[9.338524633],"iteration":20,"passed_time":0.06473875166,"remaining_time":3.018058946},
{"learn":[9.170203312],"iteration":21,"passed_time":0.06498846498,"remaining_time":2.889032671},
{"learn":[9.010299969],"iteration":22,"passed_time":0.06522442803,"remaining_time":2.770620269},
{"learn":[8.843866678],"iteration":23,"passed_time":0.06549197504,"remaining_time":2.663340318},
{"learn":[8.690548059],"iteration":24,"passed_time":0.06576448048,"remaining_time":2.564814739},
{"learn":[8.555307687],"iteration":25,"passed_time":0.0660288191,"remaining_time":2.473541146},
{"learn":[8.413851302],"iteration":26,"passed_time":0.066257532,"remaining_time":2.387725135},
{"learn":[8.29256019],"iteration":27,"passed_time":0.06652241229,"remaining_time":2.309278027},
{"learn":[8.162193833],"iteration":28,"passed_time":0.06679341771,"remaining_time":2.236427883},
{"learn":[8.040736294],"iteration":29,"passed_time":0.06709604875,"remaining_time":2.16943891},
{"learn":[7.921220278],"iteration":30,"passed_time":0.06745555594,"remaining_time":2.108530119},
{"learn":[7.809589039],"iteration":31,"passed_time":0.06779422937,"remaining_time":2.050775438},
{"learn":[7.699675801],"iteration":32,"passed_time":0.06810365222,"remaining_time":1.995643385},
{"learn":[7.60645267],"iteration":33,"passed_time":0.06836669914,"remaining_time":1.94241857},
{"learn":[7.498880302],"iteration":34,"passed_time":0.06864891311,"remaining_time":1.892748604},
{"learn":[7.401158744],"iteration":35,"passed_time":0.06890666826,"remaining_time":1.84516745},
{"learn":[7.306431077],"iteration":36,"passed_time":0.06915263151,"remaining_time":1.799837409},
{"learn":[7.223863468],"iteration":37,"passed_time":0.06941988684,"remaining_time":1.757419241},
{"learn":[7.143477682],"iteration":38,"passed_time":0.06964772473,"remaining_time":1.716191371},
{"learn":[7.062817131],"iteration":39,"passed_time":0.06989247962,"remaining_time":1.677419511},
{"learn":[6.990793435],"iteration":40,"passed_time":0.07013277609,"remaining_time":1.640422738},
{"learn":[6.931862224],"iteration":41,"passed_time":0.07038703117,"remaining_time":1.605494663},
{"learn":[6.858296558],"iteration":42,"passed_time":0.07064970308,"remaining_time":1.572366648},
{"learn":[6.786268161],"iteration":43,"passed_time":0.0708994164,"remaining_time":1.540450956},
{"learn":[6.717118549],"iteration":44,"passed_time":0.07114671301,"remaining_time":1.509891354},
{"learn":[6.652948106],"iteration":45,"passed_time":0.07138780116,"remaining_time":1.48052092},
{"learn":[6.589686076],"iteration":46,"passed_time":0.07161526404,"remaining_time":1.452113758},
{"learn":[6.531283097],"iteration":47,"passed_time":0.07186285232,"remaining_time":1.425279904},
{"learn":[6.471368031],"iteration":48,"passed_time":0.07209827369,"remaining_time":1.399295067},
{"learn":[6.416481395],"iteration":49,"passed_time":0.07232969498,"remaining_time":1.374264205},
{"learn":[6.369870822],"iteration":50,"passed_time":0.07257353318,"remaining_time":1.350436921},
{"learn":[6.325678067],"iteration":51,"passed_time":0.0728031211,"remaining_time":1.3272569},
{"learn":[6.275766122],"iteration":52,"passed_time":0.07303025064,"remaining_time":1.304899007},
{"learn":[6.224773967],"iteration":53,"passed_time":0.07331646469,"remaining_time":1.284395844},
{"learn":[6.182249254],"iteration":54,"passed_time":0.07356046956,"remaining_time":1.263902613},
{"learn":[6.139904173],"iteration":55,"passed_time":0.07380459944,"remaining_time":1.244134676},
{"learn":[6.100525536],"iteration":56,"passed_time":0.07404710429,"remaining_time":1.225024901},
{"learn":[6.062568564],"iteration":57,"passed_time":0.07428044228,"remaining_time":1.206416838},
{"learn":[6.030559288],"iteration":58,"passed_time":0.07450919685,"remaining_time":1.188358546},
{"learn":[5.997931376],"iteration":59,"passed_time":0.07474786828,"remaining_time":1.171049936},
{"learn":[5.964103835],"iteration":60,"passed_time":0.07498345632,"remaining_time":1.154253533},
{"learn":[5.933729724],"iteration":61,"passed_time":0.07523450301,"remaining_time":1.138225223},
{"learn":[5.901932711],"iteration":62,"passed_time":0.07545088233,"remaining_time":1.122182171},
{"learn":[5.873727795],"iteration":63,"passed_time":0.07567572015,"remaining_time":1.106757407},
{"learn":[5.846485734],"iteration":64,"passed_time":0.0759198917,"remaining_time":1.092078442},
{"learn":[5.820630862],"iteration":65,"passed_time":0.07613868774,"remaining_time":1.077477793},
{"learn":[5.793646238],"iteration":66,"passed_time":0.07638169259,"remaining_time":1.06364357},
{"learn":[5.765388646],"iteration":67,"passed_time":0.07661419724,"remaining_time":1.050065174},
{"learn":[5.747073912],"iteration":68,"passed_time":0.07683991008,"remaining_time":1.036781975},
{"learn":[5.722315217],"iteration":69,"passed_time":0.07706724795,"remaining_time":1.023893437},
{"learn":[5.699970599],"iteration":70,"passed_time":0.07730608606,"remaining_time":1.011512027},
{"learn":[5.682732647],"iteration":71,"passed_time":0.07752788216,"remaining_time":0.9992482589},
{"learn":[5.663525791],"iteration":72,"passed_time":0.07781247118,"remaining_time":0.9881117915},
{"learn":[5.642381613],"iteration":73,"passed_time":0.07804222576,"remaining_time":0.9765824467},
{"learn":[5.621404779],"iteration":74,"passed_time":0.07826914697,"remaining_time":0.9653194792},
{"learn":[5.602460129],"iteration":75,"passed_time":0.0784960265,"remaining_time":0.9543464274},
{"learn":[5.587337574],"iteration":76,"passed_time":0.07872786446,"remaining_time":0.9437119338},
{"learn":[5.572393026],"iteration":77,"passed_time":0.07897207767,"remaining_time":0.9334904566},
{"learn":[5.558425806],"iteration":78,"passed_time":0.07920829073,"remaining_time":0.9234283008},
{"learn":[5.541518902],"iteration":79,"passed_time":0.0794440871,"remaining_time":0.9136070017},
{"learn":[5.526157283],"iteration":80,"passed_time":0.07968975868,"remaining_time":0.9041344225},
{"learn":[5.511746977],"iteration":81,"passed_time":0.07991763823,"remaining_time":0.8946877061},
{"learn":[5.504975022],"iteration":82,"passed_time":0.08001001508,"remaining_time":0.8839660702},
{"learn":[5.493980522],"iteration":83,"passed_time":0.08023072782,"remaining_time":0.8748969843},
{"learn":[5.480745463],"iteration":84,"passed_time":0.08046669087,"remaining_time":0.8662002605},
{"learn":[5.464052013],"iteration":85,"passed_time":0.08070502896,"remaining_time":0.8577255404},
{"learn":[5.449143727],"iteration":86,"passed_time":0.08093678359,"remaining_time":0.8493710738},
{"learn":[5.438255432],"iteration":87,"passed_time":0.08117678839,"remaining_time":0.841286716},
{"learn":[5.425927931],"iteration":88,"passed_time":0.08139220936,"remaining_time":0.8331269969},
{"learn":[5.412331217],"iteration":89,"passed_time":0.08164567275,"remaining_time":0.825528469},
{"learn":[5.400691499],"iteration":90,"passed_time":0.08186171874,"remaining_time":0.817717608},
{"learn":[5.391618744],"iteration":91,"passed_time":0.08207959809,"remaining_time":0.8100899464},
{"learn":[5.380766572],"iteration":92,"passed_time":0.08231785285,"remaining_time":0.8028203498},
{"learn":[5.372207183],"iteration":93,"passed_time":0.08254019062,"remaining_time":0.7955469437},
{"learn":[5.362918837],"iteration":94,"passed_time":0.08284819678,"remaining_time":0.7892380851},
{"learn":[5.348292324],"iteration":95,"passed_time":0.08314761943,"remaining_time":0.7829734163},
{"learn":[5.339772295],"iteration":96,"passed_time":0.08338558251,"remaining_time":0.776259598},
{"learn":[5.331515983],"iteration":97,"passed_time":0.08363167076,"remaining_time":0.7697527248},
{"learn":[5.323861644],"iteration":98,"passed_time":0.08385980032,"remaining_time":0.7632088898},
{"learn":[5.313277281],"iteration":99,"passed_time":0.08407655465,"remaining_time":0.7566889918},
{"learn":[5.30685627],"iteration":100,"passed_time":0.08430235083,"remaining_time":0.75037439},
{"learn":[5.29652059],"iteration":101,"passed_time":0.08452585529,"remaining_time":0.7441590005},
{"learn":[5.288350766],"iteration":102,"passed_time":0.08475690157,"remaining_time":0.738125638},
{"learn":[5.27993346],"iteration":103,"passed_time":0.08497990603,"remaining_time":0.732134575},
{"learn":[5.271789139],"iteration":104,"passed_time":0.08519920208,"remaining_time":0.7262217701},
{"learn":[5.262684686],"iteration":105,"passed_time":0.08545899893,"remaining_time":0.7207579721},
{"learn":[5.251619772],"iteration":106,"passed_time":0.08569525365,"remaining_time":0.7151949674},
{"learn":[5.241012171],"iteration":107,"passed_time":0.08589863272,"remaining_time":0.7094590776},
{"learn":[5.232684032],"iteration":108,"passed_time":0.08612105383,"remaining_time":0.7039803574},
{"learn":[5.224267141],"iteration":109,"passed_time":0.08634989173,"remaining_time":0.698649124},
{"learn":[5.216324968],"iteration":110,"passed_time":0.08658477142,"remaining_time":0.6934582144},
{"learn":[5.211102527],"iteration":111,"passed_time":0.0868486517,"remaining_time":0.6885857385},
{"learn":[5.206364257],"iteration":112,"passed_time":0.08707244783,"remaining_time":0.6834801879},
{"learn":[5.196937641],"iteration":113,"passed_time":0.08731778607,"remaining_time":0.6786277058},
{"learn":[5.190746047],"iteration":114,"passed_time":0.08753874882,"remaining_time":0.6736677626},
{"learn":[5.181885213],"iteration":115,"passed_time":0.08776137826,"remaining_time":0.6688022275},
{"learn":[5.178293568],"iteration":116,"passed_time":0.08791896475,"remaining_time":0.6635251784},
{"learn":[5.170991438],"iteration":117,"passed_time":0.08819422024,"remaining_time":0.6592144259},
{"learn":[5.166257212],"iteration":118,"passed_time":0.08842622488,"remaining_time":0.6546512951},
{"learn":[5.161421246],"iteration":119,"passed_time":0.08867110477,"remaining_time":0.6502547683},
{"learn":[5.158223542],"iteration":120,"passed_time":0.08894981867,"remaining_time":0.6461726497},
{"learn":[5.15470988],"iteration":121,"passed_time":0.08911307193,"remaining_time":0.6413219439},
{"learn":[5.146388143],"iteration":122,"passed_time":0.08935049334,"remaining_time":0.6370762818},
{"learn":[5.139529364],"iteration":123,"passed_time":0.08962320713,"remaining_time":0.6331445923},
{"learn":[5.134276023],"iteration":124,"passed_time":0.08985312839,"remaining_time":0.6289718987},
{"learn":[5.128536065],"iteration":125,"passed_time":0.0901027167,"remaining_time":0.6249982095},
{"learn":[5.123300353],"iteration":126,"passed_time":0.09026496995,"remaining_time":0.6204828249},
{"learn":[5.116200518],"iteration":127,"passed_time":0.09050943316,"remaining_time":0.6165955134},
{"learn":[5.108728704],"iteration":128,"passed_time":0.09074868794,"remaining_time":0.6127295132},
{"learn":[5.104075866],"iteration":129,"passed_time":0.09097602582,"remaining_time":0.6088395574},
{"learn":[5.100317606],"iteration":130,"passed_time":0.09123582268,"remaining_time":0.605220839},
{"learn":[5.095814182],"iteration":131,"passed_time":0.09146278554,"remaining_time":0.6014371049},
{"learn":[5.092146915],"iteration":132,"passed_time":0.0916993736,"remaining_time":0.5977696009},
{"learn":[5.085258329],"iteration":133,"passed_time":0.0919346283,"remaining_time":0.5941446874},
{"learn":[5.079219421],"iteration":134,"passed_time":0.09216829964,"remaining_time":0.5905598458},
{"learn":[5.076476829],"iteration":135,"passed_time":0.0924068044,"remaining_time":0.5870549927},
{"learn":[5.072133867],"iteration":136,"passed_time":0.09265568437,"remaining_time":0.5836631797},
{"learn":[5.067031564],"iteration":137,"passed_time":0.09289535583,"remaining_time":0.5802593966},
{"learn":[5.061358312],"iteration":138,"passed_time":0.09313640231,"remaining_time":0.5769096575},
{"learn":[5.056759124],"iteration":139,"passed_time":0.09335840675,"remaining_time":0.5734873557},
{"learn":[5.050254],"iteration":140,"passed_time":0.09361149514,"remaining_time":0.5702998179},
{"learn":[5.048376474],"iteration":141,"passed_time":0.09372562242,"remaining_time":0.5663139721},
{"learn":[5.042603751],"iteration":142,"passed_time":0.09396475219,"remaining_time":0.563131417},
{"learn":[5.037477349],"iteration":143,"passed_time":0.09421096544,"remaining_time":0.5600318501},
{"learn":[5.03230489],"iteration":144,"passed_time":0.09444372009,"remaining_time":0.5568922806},
{"learn":[5.025976187],"iteration":145,"passed_time":0.09468639161,"remaining_time":0.5538505372},
{"learn":[5.01952451],"iteration":146,"passed_time":0.0949843559,"remaining_time":0.551167725},
{"learn":[5.017569424],"iteration":147,"passed_time":0.09520644367,"remaining_time":0.5480803379},
{"learn":[5.008962367],"iteration":148,"passed_time":0.0954434484,"remaining_time":0.545116608},
{"learn":[5.003880266],"iteration":149,"passed_time":0.09567820309,"remaining_time":0.5421764842},
{"learn":[4.996387564],"iteration":150,"passed_time":0.09592208296,"remaining_time":0.5393234996},
{"learn":[4.993361683],"iteration":151,"passed_time":0.09625238123,"remaining_time":0.536986969},
{"learn":[4.99005752],"iteration":152,"passed_time":0.09647767739,"remaining_time":0.5340953775},
{"learn":[4.986908764],"iteration":153,"passed_time":0.09670480693,"remaining_time":0.5312484848},
{"learn":[4.985207175],"iteration":154,"passed_time":0.09693185313,"remaining_time":0.5284349413},
{"learn":[4.979003494],"iteration":155,"passed_time":0.09720181686,"remaining_time":0.5258867528},
{"learn":[4.973142217],"iteration":156,"passed_time":0.09746303041,"remaining_time":0.5233206028},
{"learn":[4.967056696],"iteration":157,"passed_time":0.09781499578,"remaining_time":0.521267256},
{"learn":[4.961460696],"iteration":158,"passed_time":0.09814879411,"remaining_time":0.5191392192},
{"learn":[4.954240363],"iteration":159,"passed_time":0.09837554864,"remaining_time":0.5164716304},
{"learn":[4.952320707],"iteration":160,"passed_time":0.09856659413,"remaining_time":0.5136482762},
{"learn":[4.948337777],"iteration":161,"passed_time":0.0987903486,"remaining_time":0.511026618},
{"learn":[4.943228639],"iteration":162,"passed_time":0.09900656125,"remaining_time":0.508395655},
{"learn":[4.938545759],"iteration":163,"passed_time":0.09924560769,"remaining_time":0.5059105368},
{"learn":[4.935330572],"iteration":164,"passed_time":0.09945344518,"remaining_time":0.5032947074},
{"learn":[4.932051543],"iteration":165,"passed_time":0.09970386685,"remaining_time":0.500921837},
{"learn":[4.928964153],"iteration":166,"passed_time":0.09992416291,"remaining_time":0.498424118},
{"learn":[4.922860227],"iteration":167,"passed_time":0.1001379589,"remaining_time":0.49592132},
{"learn":[4.917668772],"iteration":168,"passed_time":0.1003524631,"remaining_time":0.4934490939},
{"learn":[4.910365386],"iteration":169,"passed_time":0.1005785093,"remaining_time":0.4910597808},
{"learn":[4.906457206],"iteration":170,"passed_time":0.1008085556,"remaining_time":0.4887151613},
{"learn":[4.901996508],"iteration":171,"passed_time":0.1011504791,"remaining_time":0.4869337016},
{"learn":[4.896816173],"iteration":172,"passed_time":0.1013939839,"remaining_time":0.4846984088},
{"learn":[4.891123132],"iteration":173,"passed_time":0.1016217385,"remaining_time":0.4824112414},
{"learn":[4.887630202],"iteration":174,"passed_time":0.1018626183,"remaining_time":0.4802094863},
{"learn":[4.885259712],"iteration":175,"passed_time":0.1020959563,"remaining_time":0.4779947045},
{"learn":[4.880659728],"iteration":176,"passed_time":0.1023134606,"remaining_time":0.4757286899},
{"learn":[4.877299723],"iteration":177,"passed_time":0.102579341,"remaining_time":0.4737090914},
{"learn":[4.874038772],"iteration":178,"passed_time":0.1028018871,"remaining_time":0.4715103312},
{"learn":[4.86943698],"iteration":179,"passed_time":0.1030355584,"remaining_time":0.4693842105},
{"learn":[4.861268711],"iteration":180,"passed_time":0.1032889801,"remaining_time":0.4673683687},
{"learn":[4.858673056],"iteration":181,"passed_time":0.103550277,"remaining_time":0.465407289},
{"learn":[4.854036207],"iteration":182,"passed_time":0.1037986987,"remaining_time":0.4634073049},
{"learn":[4.85130244],"iteration":183,"passed_time":0.1040498703,"remaining_time":0.4614385554},
{"learn":[4.847510084],"iteration":184,"passed_time":0.1042709998,"remaining_time":0.4593560259},
{"learn":[4.845691673],"iteration":185,"passed_time":0.1044759622,"remaining_time":0.4572227592},
{"learn":[4.842058646],"iteration":186,"passed_time":0.1047140919,"remaining_time":0.4552543142},
{"learn":[4.838623675],"iteration":187,"passed_time":0.1049393464,"remaining_time":0.4532486665},
{"learn":[4.834602161],"iteration":188,"passed_time":0.1051705594,"remaining_time":0.4512874268},
{"learn":[4.830858976],"iteration":189,"passed_time":0.1053884804,"remaining_time":0.4492877323},
{"learn":[4.827590511],"iteration":190,"passed_time":0.105600568,"remaining_time":0.4472819869},
{"learn":[4.822246226],"iteration":191,"passed_time":0.1058464896,"remaining_time":0.4454373102},
{"learn":[4.816686395],"iteration":192,"passed_time":0.1060887861,"remaining_time":0.4435940433},
{"learn":[4.814797121],"iteration":193,"passed_time":0.1063144156,"remaining_time":0.4416980358},
{"learn":[4.811639392],"iteration":194,"passed_time":0.1065452119,"remaining_time":0.43984049},
{"learn":[4.804813432],"iteration":195,"passed_time":0.1068378427,"remaining_time":0.4382531915},
{"learn":[4.80251613],"iteration":196,"passed_time":0.1070626389,"remaining_time":0.436402533},
{"learn":[4.800087884],"iteration":197,"passed_time":0.1072990186,"remaining_time":0.4346152167},
{"learn":[4.794773135],"iteration":198,"passed_time":0.107538815,"remaining_time":0.4328572404},
{"learn":[4.791664833],"iteration":199,"passed_time":0.1077801115,"remaining_time":0.4311204461},
{"learn":[4.785989873],"iteration":200,"passed_time":0.1080072411,"remaining_time":0.429342217},
{"learn":[4.782387142],"iteration":201,"passed_time":0.1082352456,"remaining_time":0.427582802},
{"learn":[4.778623704],"iteration":202,"passed_time":0.1084698753,"remaining_time":0.4258644858},
{"learn":[4.775772178],"iteration":203,"passed_time":0.1087029216,"remaining_time":0.4241545373},
{"learn":[4.77023101],"iteration":204,"passed_time":0.1089293428,"remaining_time":0.4224333051},
{"learn":[4.764496689],"iteration":205,"passed_time":0.1091488472,"remaining_time":0.4206999256},
{"learn":[4.763138716],"iteration":206,"passed_time":0.1093853936,"remaining_time":0.4190464595},
{"learn":[4.758053283],"iteration":207,"passed_time":0.1096108564,"remaining_time":0.4173644149},
{"learn":[4.755063788],"iteration":208,"passed_time":0.1098464445,"remaining_time":0.4157346296},
{"learn":[4.752465267],"iteration":209,"passed_time":0.1100823659,"remaining_time":0.4141193763},
{"learn":[4.748067377],"iteration":210,"passed_time":0.1103128288,"remaining_time":0.4124967863},
{"learn":[4.744163298],"iteration":211,"passed_time":0.1105338332,"remaining_time":0.4108521725},
{"learn":[4.736670896],"iteration":212,"passed_time":0.110771713,"remaining_time":0.4092832774},
{"learn":[4.73349255],"iteration":213,"passed_time":0.1110565103,"remaining_time":0.4078991454},
{"learn":[4.731864595],"iteration":214,"passed_time":0.1113940587,"remaining_time":0.4067178423},
{"learn":[4.728398311],"iteration":215,"passed_time":0.1116316051,"remaining_time":0.4051813816},
{"learn":[4.723865975],"iteration":216,"passed_time":0.1118512762,"remaining_time":0.4035923929},
{"learn":[4.723483365],"iteration":217,"passed_time":0.1120985728,"remaining_time":0.4021150639},
{"learn":[4.72095416],"iteration":218,"passed_time":0.1123632031,"remaining_time":0.4007107836},
{"learn":[4.716173382],"iteration":219,"passed_time":0.1126932097,"remaining_time":0.3995486525},
{"learn":[4.710563974],"iteration":220,"passed_time":0.1129357145,"remaining_time":0.3980856182},
{"learn":[4.707160263],"iteration":221,"passed_time":0.1131631774,"remaining_time":0.3965808649},
{"learn":[4.70408351],"iteration":222,"passed_time":0.1134093907,"remaining_time":0.3951528993},
{"learn":[4.702501831],"iteration":223,"passed_time":0.1136478121,"remaining_time":0.3937084918},
{"learn":[4.700269738],"iteration":224,"passed_time":0.1139896939,"remaining_time":0.3926311679},
{"learn":[4.695346302],"iteration":225,"passed_time":0.1142325321,"remaining_time":0.3912211497},
{"learn":[4.689769299],"iteration":226,"passed_time":0.1144538698,"remaining_time":0.3897482},
{"learn":[4.687919514],"iteration":227,"passed_time":0.1146931663,"remaining_time":0.3883470368},
{"learn":[4.682982074],"iteration":228,"passed_time":0.1149192541,"remaining_time":0.38691155},
{"learn":[4.679578702],"iteration":229,"passed_time":0.1151494254,"remaining_time":0.3855002503},
{"learn":[4.675751423],"iteration":230,"passed_time":0.1153580129,"remaining_time":0.3840273244},
{"learn":[4.672710726],"iteration":231,"passed_time":0.1156058095,"remaining_time":0.3826950936},
{"learn":[4.6690533],"iteration":232,"passed_time":0.1158212722,"remaining_time":0.3812657328},
{"learn":[4.667595702],"iteration":233,"passed_time":0.1160446933,"remaining_time":0.3798727994},
{"learn":[4.664241291],"iteration":234,"passed_time":0.1162530308,"remaining_time":0.3784407173},
{"learn":[4.662246999],"iteration":235,"passed_time":0.1164724102,"remaining_time":0.3770547516},
{"learn":[4.658668443],"iteration":236,"passed_time":0.116698873,"remaining_time":0.3757014351},
{"learn":[4.658017572],"iteration":237,"passed_time":0.1169058772,"remaining_time":0.3742952874},
{"learn":[4.657656705],"iteration":238,"passed_time":0.11713159,"remaining_time":0.3729587448},
{"learn":[4.653242871],"iteration":239,"passed_time":0.1173599279,"remaining_time":0.3716397717},
{"learn":[4.6507302],"iteration":240,"passed_time":0.1176198914,"remaining_time":0.3704294506},
{"learn":[4.647671336],"iteration":241,"passed_time":0.1179381895,"remaining_time":0.3694097009},
{"learn":[4.645506007],"iteration":242,"passed_time":0.118164444,"remaining_time":0.368108988},
{"learn":[4.641297906],"iteration":243,"passed_time":0.1183988237,"remaining_time":0.3668422569},
{"learn":[4.63798107],"iteration":244,"passed_time":0.1186377451,"remaining_time":0.3655979492},
{"learn":[4.635062318],"iteration":245,"passed_time":0.1188794583,"remaining_time":0.3643703721},
{"learn":[4.631606017],"iteration":246,"passed_time":0.1191086295,"remaining_time":0.3631125426},
{"learn":[4.630215494],"iteration":247,"passed_time":0.1193281339,"remaining_time":0.3618336963},
{"learn":[4.62729814],"iteration":248,"passed_time":0.1195616386,"remaining_time":0.3606055846},
{"learn":[4.624691756],"iteration":249,"passed_time":0.1197946849,"remaining_time":0.3593840546},
{"learn":[4.621840053],"iteration":250,"passed_time":0.1200128976,"remaining_time":0.3581261366},
{"learn":[4.619602091],"iteration":251,"passed_time":0.1202383187,"remaining_time":0.3568978667},
{"learn":[4.613584029],"iteration":252,"passed_time":0.1204619482,"remaining_time":0.3556722344},
{"learn":[4.6119388],"iteration":253,"passed_time":0.1206964529,"remaining_time":0.3544864325},
{"learn":[4.60870702],"iteration":254,"passed_time":0.1209085405,"remaining_time":0.3532425986},
{"learn":[4.604771557],"iteration":255,"passed_time":0.1211471702,"remaining_time":0.3520839635},
{"learn":[4.604231277],"iteration":256,"passed_time":0.1213778415,"remaining_time":0.3509094795},
{"learn":[4.600750354],"iteration":257,"passed_time":0.1215982209,"remaining_time":0.3497127129},
{"learn":[4.596488253],"iteration":258,"passed_time":0.1218259755,"remaining_time":0.3485445862},
{"learn":[4.59470784],"iteration":259,"passed_time":0.1220433131,"remaining_time":0.3473540451},
{"learn":[4.588818005],"iteration":260,"passed_time":0.1222779428,"remaining_time":0.3462199224},
{"learn":[4.585054174],"iteration":261,"passed_time":0.1224976139,"remaining_time":0.3450505307},
{"learn":[4.581471435],"iteration":262,"passed_time":0.122754244,"remaining_time":0.3439919309},
{"learn":[4.577555199],"iteration":263,"passed_time":0.1230071657,"remaining_time":0.3429290681},
{"learn":[4.57457145],"iteration":264,"passed_time":0.1232233784,"remaining_time":0.3417705023},
{"learn":[4.573029224],"iteration":265,"passed_time":0.1234507579,"remaining_time":0.3406498358},
{"learn":[4.571326203],"iteration":266,"passed_time":0.1236656789,"remaining_time":0.3395016577},
{"learn":[4.571019224],"iteration":267,"passed_time":0.1239166006,"remaining_time":0.3384587747},
{"learn":[4.565766631],"iteration":268,"passed_time":0.1241479802,"remaining_time":0.3373686748},
{"learn":[4.563383471],"iteration":269,"passed_time":0.1244028186,"remaining_time":0.3363483614},
{"learn":[4.558165805],"iteration":270,"passed_time":0.1246192396,"remaining_time":0.335230353},
{"learn":[4.55629209],"iteration":271,"passed_time":0.1248392857,"remaining_time":0.3341286763},
{"learn":[4.549383848],"iteration":272,"passed_time":0.1250819155,"remaining_time":0.3330935992},
{"learn":[4.546227503],"iteration":273,"passed_time":0.1253251287,"remaining_time":0.332065852},
{"learn":[4.540620977],"iteration":274,"passed_time":0.1255545083,"remaining_time":0.33100734},
{"learn":[4.532898237],"iteration":275,"passed_time":0.1258323055,"remaining_time":0.3300818449},
{"learn":[4.529757367],"iteration":276,"passed_time":0.1260673519,"remaining_time":0.3290494419},
{"learn":[4.52579294],"iteration":277,"passed_time":0.126308315,"remaining_time":0.3280381419},
{"learn":[4.521572155],"iteration":278,"passed_time":0.1265509032,"remaining_time":0.3270365634},
{"learn":[4.518818099],"iteration":279,"passed_time":0.1267760327,"remaining_time":0.3259955126},
{"learn":[4.514012334],"iteration":280,"passed_time":0.1270640801,"remaining_time":0.3251212583},
{"learn":[4.508331416],"iteration":281,"passed_time":0.1273071683,"remaining_time":0.3241366909},
{"learn":[4.506038537],"iteration":282,"passed_time":0.1275527982,"remaining_time":0.3231638032},
{"learn":[4.505805643],"iteration":283,"passed_time":0.1277743443,"remaining_time":0.3221353187},
{"learn":[4.501550352],"iteration":284,"passed_time":0.1280427663,"remaining_time":0.321230098},
{"learn":[4.494692643],"iteration":285,"passed_time":0.1282818128,"remaining_time":0.3202559941},
{"learn":[4.489330245],"iteration":286,"passed_time":0.128527776,"remaining_time":0.3193041962},
{"learn":[4.484826955],"iteration":287,"passed_time":0.128775156,"remaining_time":0.3183608022},
{"learn":[4.478285428],"iteration":288,"passed_time":0.1289828268,"remaining_time":0.3173245323},
{"learn":[4.475311671],"iteration":289,"passed_time":0.1292170398,"remaining_time":0.3163589595},
{"learn":[4.471581298],"iteration":290,"passed_time":0.1294363775,"remaining_time":0.3153621706},
{"learn":[4.469164956],"iteration":291,"passed_time":0.1297330084,"remaining_time":0.3145581163},
{"learn":[4.462068024],"iteration":292,"passed_time":0.1300139307,"remaining_time":0.3137196212},
{"learn":[4.458540976],"iteration":293,"passed_time":0.1302565606,"remaining_time":0.3127929651},
{"learn":[4.455757458],"iteration":294,"passed_time":0.1304963153,"remaining_time":0.3118640756},
{"learn":[4.453027414],"iteration":295,"passed_time":0.1307164031,"remaining_time":0.3108930668},
{"learn":[4.450659338],"iteration":296,"passed_time":0.1309632413,"remaining_time":0.3099904332},
{"learn":[4.444696901],"iteration":297,"passed_time":0.1312096629,"remaining_time":0.3090912194},
{"learn":[4.442052813],"iteration":298,"passed_time":0.1314318757,"remaining_time":0.3081396149},
{"learn":[4.440036756],"iteration":299,"passed_time":0.1316577135,"remaining_time":0.3072013316},
{"learn":[4.435017051],"iteration":300,"passed_time":0.1319175937,"remaining_time":0.3063468373},
{"learn":[4.429962125],"iteration":301,"passed_time":0.1321387648,"remaining_time":0.3054068141},
{"learn":[4.427666256],"iteration":302,"passed_time":0.1323556025,"remaining_time":0.3044615674},
{"learn":[4.425030004],"iteration":303,"passed_time":0.1325828154,"remaining_time":0.3035448667},
{"learn":[4.422588771],"iteration":304,"passed_time":0.1327881945,"remaining_time":0.3025829349},
{"learn":[4.418936667],"iteration":305,"passed_time":0.133013449,"remaining_time":0.3016710248},
{"learn":[4.416887976],"iteration":306,"passed_time":0.1332503287,"remaining_time":0.3007898299},
{"learn":[4.413773354],"iteration":307,"passed_time":0.133499417,"remaining_time":0.2999402486},
{"learn":[4.411129391],"iteration":308,"passed_time":0.1337228381,"remaining_time":0.2990371558},
{"learn":[4.40850819],"iteration":309,"passed_time":0.1339486343,"remaining_time":0.2981437344},
{"learn":[4.404880292],"iteration":310,"passed_time":0.1341755138,"remaining_time":0.2972570065},
{"learn":[4.404593827],"iteration":311,"passed_time":0.1344035601,"remaining_time":0.2963770812},
{"learn":[4.402139942],"iteration":312,"passed_time":0.1346668987,"remaining_time":0.295578784},
{"learn":[4.400284725],"iteration":313,"passed_time":0.1348843197,"remaining_time":0.2946835774},
{"learn":[4.395805521],"iteration":314,"passed_time":0.1351278245,"remaining_time":0.2938493962},
{"learn":[4.392838833],"iteration":315,"passed_time":0.1353479123,"remaining_time":0.2929682658},
{"learn":[4.389213061],"iteration":316,"passed_time":0.1355863337,"remaining_time":0.2921308073},
{"learn":[4.3861981],"iteration":317,"passed_time":0.1358157966,"remaining_time":0.2912779034},
{"learn":[4.385054234],"iteration":318,"passed_time":0.1360467179,"remaining_time":0.2904320216},
{"learn":[4.379364607],"iteration":319,"passed_time":0.1362977229,"remaining_time":0.2896326612},
{"learn":[4.378387619],"iteration":320,"passed_time":0.1365241441,"remaining_time":0.288784716},
{"learn":[4.375816727],"iteration":321,"passed_time":0.1367433985,"remaining_time":0.2879255409},
{"learn":[4.374600202],"iteration":322,"passed_time":0.1369513193,"remaining_time":0.2870465733},
{"learn":[4.37098897],"iteration":323,"passed_time":0.1371771571,"remaining_time":0.2862091303},
{"learn":[4.367418484],"iteration":324,"passed_time":0.1374351623,"remaining_time":0.2854422602},
{"learn":[4.363584638],"iteration":325,"passed_time":0.1376576251,"remaining_time":0.2846050285},
{"learn":[4.360770706],"iteration":326,"passed_time":0.1378935048,"remaining_time":0.2837991704},
{"learn":[4.358675808],"iteration":327,"passed_time":0.1381047173,"remaining_time":0.2829462502},
{"learn":[4.354228195],"iteration":328,"passed_time":0.1383249717,"remaining_time":0.2821156718},
{"learn":[4.353773425],"iteration":329,"passed_time":0.1385593931,"remaining_time":0.2813175557},
{"learn":[4.351648009],"iteration":330,"passed_time":0.1388028146,"remaining_time":0.2805410362},
{"learn":[4.348209927],"iteration":331,"passed_time":0.1390484862,"remaining_time":0.2797722553},
{"learn":[4.345852733],"iteration":332,"passed_time":0.1392651572,"remaining_time":0.2789485281},
{"learn":[4.34237339],"iteration":333,"passed_time":0.1394785781,"remaining_time":0.2781219552},
{"learn":[4.340814362],"iteration":334,"passed_time":0.1396904157,"remaining_time":0.2772958998},
{"learn":[4.339707068],"iteration":335,"passed_time":0.1399450041,"remaining_time":0.2765579843},
{"learn":[4.335430786],"iteration":336,"passed_time":0.1402552186,"remaining_time":0.2759323737},
{"learn":[4.33521887],"iteration":337,"passed_time":0.1405316825,"remaining_time":0.2752425261},
{"learn":[4.328507238],"iteration":338,"passed_time":0.1408823978,"remaining_time":0.2746998967},
{"learn":[4.326140732],"iteration":339,"passed_time":0.1412102377,"remaining_time":0.2741139909},
{"learn":[4.323785636],"iteration":340,"passed_time":0.1414914517,"remaining_time":0.2734394916},
{"learn":[4.320632534],"iteration":341,"passed_time":0.1418003328,"remaining_time":0.2728205234},
{"learn":[4.31973724],"iteration":342,"passed_time":0.1420186705,"remaining_time":0.2720299316},
{"learn":[4.318000924],"iteration":343,"passed_time":0.1422484251,"remaining_time":0.2712644386},
{"learn":[4.312713628],"iteration":344,"passed_time":0.1424681795,"remaining_time":0.2704830654},
{"learn":[4.308220789],"iteration":345,"passed_time":0.1427032675,"remaining_time":0.2697339219},
{"learn":[4.305890947],"iteration":346,"passed_time":0.142925897,"remaining_time":0.2689642961},
{"learn":[4.305137856],"iteration":347,"passed_time":0.1431502765,"remaining_time":0.2682010927},
{"learn":[4.304787172],"iteration":348,"passed_time":0.1433707809,"remaining_time":0.2674337489},
{"learn":[4.30350134],"iteration":349,"passed_time":0.1436002855,"remaining_time":0.2666862444},
{"learn":[4.30293809],"iteration":350,"passed_time":0.1438456654,"remaining_time":0.2659710451},
{"learn":[4.299548459],"iteration":351,"passed_time":0.1441712552,"remaining_time":0.2654061743},
{"learn":[4.294768408],"iteration":352,"passed_time":0.1444331354,"remaining_time":0.2647258885},
{"learn":[4.294581479],"iteration":353,"passed_time":0.144694224,"remaining_time":0.2640465217},
{"learn":[4.292551604],"iteration":354,"passed_time":0.1449395622,"remaining_time":0.2633408947},
{"learn":[4.288628894],"iteration":355,"passed_time":0.1452019841,"remaining_time":0.2626687578},
{"learn":[4.287802767],"iteration":356,"passed_time":0.1454070716,"remaining_time":0.2618956499},
{"learn":[4.284566905],"iteration":357,"passed_time":0.1456527848,"remaining_time":0.2611985694},
{"learn":[4.27890232],"iteration":358,"passed_time":0.1458839977,"remaining_time":0.260478113},
{"learn":[4.276938023],"iteration":359,"passed_time":0.1461728785,"remaining_time":0.2598628951},
{"learn":[4.273425094],"iteration":360,"passed_time":0.1465365525,"remaining_time":0.2593818754},
{"learn":[4.269726505],"iteration":361,"passed_time":0.1468003077,"remaining_time":0.2587254042},
{"learn":[4.265565857],"iteration":362,"passed_time":0.1470447293,"remaining_time":0.2580371695},
{"learn":[4.262117173],"iteration":363,"passed_time":0.1472804006,"remaining_time":0.2573360846},
{"learn":[4.259185148],"iteration":364,"passed_time":0.1475870734,"remaining_time":0.256761073},
{"learn":[4.257668507],"iteration":365,"passed_time":0.1478777042,"remaining_time":0.256159739},
{"learn":[4.253432436],"iteration":366,"passed_time":0.1480905002,"remaining_time":0.2554258491},
{"learn":[4.250216667],"iteration":367,"passed_time":0.1483635473,"remaining_time":0.254798266},
{"learn":[4.24514828],"iteration":368,"passed_time":0.1486028854,"remaining_time":0.2541149612},
{"learn":[4.244015772],"iteration":369,"passed_time":0.1488393485,"remaining_time":0.2534291609},
{"learn":[4.240329192],"iteration":370,"passed_time":0.1490751032,"remaining_time":0.2527445819},
{"learn":[4.236718014],"iteration":371,"passed_time":0.1493366917,"remaining_time":0.252106028},
{"learn":[4.233495944],"iteration":372,"passed_time":0.149649823,"remaining_time":0.2515561368},
{"learn":[4.230357491],"iteration":373,"passed_time":0.1498776192,"remaining_time":0.2508646781},
{"learn":[4.227381215],"iteration":374,"passed_time":0.1500945819,"remaining_time":0.2501576364},
{"learn":[4.226169067],"iteration":375,"passed_time":0.1503112529,"remaining_time":0.2494527175},
{"learn":[4.225963861],"iteration":376,"passed_time":0.1505647163,"remaining_time":0.2488111889},
{"learn":[4.224346548],"iteration":377,"passed_time":0.1507799289,"remaining_time":0.2481087719},
{"learn":[4.222595381],"iteration":378,"passed_time":0.1509913081,"remaining_time":0.2474026447},
{"learn":[4.219700938],"iteration":379,"passed_time":0.1512214377,"remaining_time":0.2467297142},
{"learn":[4.216356207],"iteration":380,"passed_time":0.1514445672,"remaining_time":0.2460477351},
{"learn":[4.214326494],"iteration":381,"passed_time":0.1516706134,"remaining_time":0.2453728771},
{"learn":[4.212901398],"iteration":382,"passed_time":0.1518909928,"remaining_time":0.2446912338},
{"learn":[4.211331091],"iteration":383,"passed_time":0.1521111638,"remaining_time":0.2440116586},
{"learn":[4.208624791],"iteration":384,"passed_time":0.1523610855,"remaining_time":0.2433819937},
{"learn":[4.204659106],"iteration":385,"passed_time":0.1525910067,"remaining_time":0.2427224822},
{"learn":[4.202968852],"iteration":386,"passed_time":0.1528257614,"remaining_time":0.2420728469},
{"learn":[4.197261935],"iteration":387,"passed_time":0.1530771415,"remaining_time":0.2414515736},
{"learn":[4.196934403],"iteration":388,"passed_time":0.1535411091,"remaining_time":0.2411661122},
{"learn":[4.192479929],"iteration":389,"passed_time":0.1539447421,"remaining_time":0.2407853659},
{"learn":[4.190243116],"iteration":390,"passed_time":0.1542962491,"remaining_time":0.2403233139},
{"learn":[4.185852431],"iteration":391,"passed_time":0.1545938801,"remaining_time":0.239778263},
{"learn":[4.180967944],"iteration":392,"passed_time":0.1548101344,"remaining_time":0.2391087827},
{"learn":[4.178283162],"iteration":393,"passed_time":0.1550503059,"remaining_time":0.2384783892},
{"learn":[4.176341157],"iteration":394,"passed_time":0.1552977275,"remaining_time":0.2378610763},
{"learn":[4.176041504],"iteration":395,"passed_time":0.1555266071,"remaining_time":0.2372173502},
{"learn":[4.175564513],"iteration":396,"passed_time":0.15575582,"remaining_time":0.2365762202},
{"learn":[4.170830274],"iteration":397,"passed_time":0.1559739077,"remaining_time":0.2359203327},
{"learn":[4.167804808],"iteration":398,"passed_time":0.156206079,"remaining_time":0.2352878533},
{"learn":[4.165860548],"iteration":399,"passed_time":0.1564267917,"remaining_time":0.2346401876},
{"learn":[4.160950571],"iteration":400,"passed_time":0.1566549629,"remaining_time":0.2340057925},
{"learn":[4.158544115],"iteration":401,"passed_time":0.1568867592,"remaining_time":0.233378811},
{"learn":[4.154448767],"iteration":402,"passed_time":0.1571088887,"remaining_time":0.2327394703},
{"learn":[4.15197457],"iteration":403,"passed_time":0.1573313098,"remaining_time":0.2321026253},
{"learn":[4.149562679],"iteration":404,"passed_time":0.157543689,"remaining_time":0.231453074},
{"learn":[4.149327961],"iteration":405,"passed_time":0.1577642351,"remaining_time":0.2308176247},
{"learn":[4.147444889],"iteration":406,"passed_time":0.1579875729,"remaining_time":0.2301882819},
{"learn":[4.147254809],"iteration":407,"passed_time":0.1582137024,"remaining_time":0.22956498},
{"learn":[4.144589165],"iteration":408,"passed_time":0.1584341235,"remaining_time":0.2289353716},
{"learn":[4.141691034],"iteration":409,"passed_time":0.1586652531,"remaining_time":0.2283231691},
{"learn":[4.138893468],"iteration":410,"passed_time":0.1589114247,"remaining_time":0.2277343775},
{"learn":[4.136964597],"iteration":411,"passed_time":0.1591250539,"remaining_time":0.2271008051},
{"learn":[4.133773523],"iteration":412,"passed_time":0.1594230599,"remaining_time":0.2265891917},
{"learn":[4.131363444],"iteration":413,"passed_time":0.1596428143,"remaining_time":0.2259678482},
{"learn":[4.130228592],"iteration":414,"passed_time":0.1598666521,"remaining_time":0.2253541963},
{"learn":[4.12884186],"iteration":415,"passed_time":0.1600931149,"remaining_time":0.2247461037},
{"learn":[4.12413494],"iteration":416,"passed_time":0.1603307864,"remaining_time":0.2241555119},
{"learn":[4.119422508],"iteration":417,"passed_time":0.1605549575,"remaining_time":0.2235478116},
{"learn":[4.117038244],"iteration":418,"passed_time":0.1607898372,"remaining_time":0.222956791},
{"learn":[4.116067631],"iteration":419,"passed_time":0.1610647177,"remaining_time":0.2224227054},
{"learn":[4.110343455],"iteration":420,"passed_time":0.161313056,"remaining_time":0.2218533478},
{"learn":[4.105604544],"iteration":421,"passed_time":0.1615603943,"remaining_time":0.2212841419},
{"learn":[4.103390131],"iteration":422,"passed_time":0.1618125243,"remaining_time":0.2207229941},
{"learn":[4.096724402],"iteration":423,"passed_time":0.1620573625,"remaining_time":0.2201533981},
{"learn":[4.093431279],"iteration":424,"passed_time":0.1623118676,"remaining_time":0.2195984091},
{"learn":[4.091412744],"iteration":425,"passed_time":0.1626581662,"remaining_time":0.219168515},
{"learn":[4.091192901],"iteration":426,"passed_time":0.1628889625,"remaining_time":0.2185840176},
{"learn":[4.088994581],"iteration":427,"passed_time":0.1631060918,"remaining_time":0.2179829077},
{"learn":[4.087845355],"iteration":428,"passed_time":0.1633280962,"remaining_time":0.2173900768},
{"learn":[4.083650279],"iteration":429,"passed_time":0.163551184,"remaining_time":0.2168004067},
{"learn":[4.079840652],"iteration":430,"passed_time":0.1637782302,"remaining_time":0.2162176636},
{"learn":[4.075707828],"iteration":431,"passed_time":0.1640004847,"remaining_time":0.2156302669},
{"learn":[4.071345409],"iteration":432,"passed_time":0.1642279892,"remaining_time":0.2150514316},
{"learn":[4.067460475],"iteration":433,"passed_time":0.1644618272,"remaining_time":0.2144824751},
{"learn":[4.064914749],"iteration":434,"passed_time":0.1646795399,"remaining_time":0.2138941151},
{"learn":[4.063823175],"iteration":435,"passed_time":0.1649067944,"remaining_time":0.2133197983},
{"learn":[4.058898471],"iteration":436,"passed_time":0.1651432158,"remaining_time":0.2127588799},
{"learn":[4.054120355],"iteration":437,"passed_time":0.1653604702,"remaining_time":0.2121748499},
{"learn":[4.052715901],"iteration":438,"passed_time":0.1655936415,"remaining_time":0.2116128312},
{"learn":[4.052114167],"iteration":439,"passed_time":0.1658047291,"remaining_time":0.2110242006},
{"learn":[4.051377267],"iteration":440,"passed_time":0.1660774845,"remaining_time":0.2105154509},
{"learn":[4.049275336],"iteration":441,"passed_time":0.1663393231,"remaining_time":0.209993987},
{"learn":[4.047099198],"iteration":442,"passed_time":0.1665605775,"remaining_time":0.2094226674},
{"learn":[4.044348685],"iteration":443,"passed_time":0.1668006656,"remaining_time":0.2088765092},
{"learn":[4.042822379],"iteration":444,"passed_time":0.1671751314,"remaining_time":0.2084993212},
{"learn":[4.041258611],"iteration":445,"passed_time":0.1675495972,"remaining_time":0.2081221455},
{"learn":[4.040044254],"iteration":446,"passed_time":0.1678026023,"remaining_time":0.2075947183},
{"learn":[4.036860137],"iteration":447,"passed_time":0.1681289838,"remaining_time":0.2071589265},
{"learn":[4.036372284],"iteration":448,"passed_time":0.1683604468,"remaining_time":0.2066071407},
{"learn":[4.03368231],"iteration":449,"passed_time":0.1686187853,"remaining_time":0.2060896264},
{"learn":[4.032439519],"iteration":450,"passed_time":0.1688477065,"remaining_time":0.205537452},
{"learn":[4.032008634],"iteration":451,"passed_time":0.1690737527,"remaining_time":0.2049832223},
{"learn":[4.030034932],"iteration":452,"passed_time":0.1692972572,"remaining_time":0.2044273723},
{"learn":[4.028173412],"iteration":453,"passed_time":0.169505803,"remaining_time":0.2038549965},
{"learn":[4.023806097],"iteration":454,"passed_time":0.1698006422,"remaining_time":0.2033875824},
{"learn":[4.020239186],"iteration":455,"passed_time":0.1701462325,"remaining_time":0.2029814703},
{"learn":[4.017384838],"iteration":456,"passed_time":0.1703651952,"remaining_time":0.2024251662},
{"learn":[4.016468229],"iteration":457,"passed_time":0.1706166585,"remaining_time":0.2019087968},
{"learn":[4.014530169],"iteration":458,"passed_time":0.1708542883,"remaining_time":0.2013772766},
{"learn":[4.012884822],"iteration":459,"passed_time":0.171077001,"remaining_time":0.200829523},
{"learn":[4.008924707],"iteration":460,"passed_time":0.1712995472,"remaining_time":0.2002829846},
{"learn":[4.008286778],"iteration":461,"passed_time":0.1715475521,"remaining_time":0.1997674958},
{"learn":[4.006444202],"iteration":462,"passed_time":0.1717830985,"remaining_time":0.1992387125},
{"learn":[4.003284363],"iteration":463,"passed_time":0.1720138948,"remaining_time":0.198705706},
{"learn":[3.999811484],"iteration":464,"passed_time":0.1723222343,"remaining_time":0.1982632158},
{"learn":[3.997483319],"iteration":465,"passed_time":0.1726385739,"remaining_time":0.1978304688},
{"learn":[3.99708333],"iteration":466,"passed_time":0.1728552449,"remaining_time":0.1972844658},
{"learn":[3.995860263],"iteration":467,"passed_time":0.173160501,"remaining_time":0.1968405695},
{"learn":[3.994131111],"iteration":468,"passed_time":0.1733865889,"remaining_time":0.1963076304},
{"learn":[3.993125499],"iteration":469,"passed_time":0.1736117183,"remaining_time":0.1957749164},
{"learn":[3.992954084],"iteration":470,"passed_time":0.1738232642,"remaining_time":0.1952282522},
{"learn":[3.990635743],"iteration":471,"passed_time":0.1740328934,"remaining_time":0.1946808638},
{"learn":[3.986678254],"iteration":472,"passed_time":0.1743038155,"remaining_time":0.194203194},
{"learn":[3.986393291],"iteration":473,"passed_time":0.174561654,"remaining_time":0.1937118776},
{"learn":[3.986152671],"iteration":474,"passed_time":0.1747858668,"remaining_time":0.1931843791},
{"learn":[3.985596662],"iteration":475,"passed_time":0.1750012878,"remaining_time":0.1926484765},
{"learn":[3.983853457],"iteration":476,"passed_time":0.175228459,"remaining_time":0.1921268009},
{"learn":[3.983263928],"iteration":477,"passed_time":0.1754621303,"remaining_time":0.1916134561},
{"learn":[3.980067202],"iteration":478,"passed_time":0.1756887598,"remaining_time":0.1910936198},
{"learn":[3.978115407],"iteration":479,"passed_time":0.1759094309,"remaining_time":0.1905685502},
{"learn":[3.972661644],"iteration":480,"passed_time":0.1761473523,"remaining_time":0.1900633594},
{"learn":[3.969938254],"iteration":481,"passed_time":0.1764248162,"remaining_time":0.1896017734},
{"learn":[3.968211434],"iteration":482,"passed_time":0.1768947839,"remaining_time":0.1893470048},
{"learn":[3.966113368],"iteration":483,"passed_time":0.1772211655,"remaining_time":0.1889382673},
{"learn":[3.962246044],"iteration":484,"passed_time":0.177481254,"remaining_time":0.1884594759},
{"learn":[3.961319703],"iteration":485,"passed_time":0.1776939666,"remaining_time":0.187931479},
{"learn":[3.96078191],"iteration":486,"passed_time":0.1779419715,"remaining_time":0.1874419536},
{"learn":[3.958913633],"iteration":487,"passed_time":0.1781640176,"remaining_time":0.1869261824},
{"learn":[3.957428286],"iteration":488,"passed_time":0.1783891471,"remaining_time":0.1864148347},
{"learn":[3.952641965],"iteration":489,"passed_time":0.1786205684,"remaining_time":0.1859112039},
{"learn":[3.951486786],"iteration":490,"passed_time":0.1788381561,"remaining_time":0.185394341},
{"learn":[3.94938344],"iteration":491,"passed_time":0.179069119,"remaining_time":0.184892505},
{"learn":[3.947297924],"iteration":492,"passed_time":0.1793137073,"remaining_time":0.1844057801},
{"learn":[3.946284886],"iteration":493,"passed_time":0.1795598788,"remaining_time":0.1839216573},
{"learn":[3.943288204],"iteration":494,"passed_time":0.1797936752,"remaining_time":0.1834258706},
{"learn":[3.943076488],"iteration":495,"passed_time":0.180053097,"remaining_time":0.1829571792},
{"learn":[3.942347078],"iteration":496,"passed_time":0.1802805599,"remaining_time":0.1824569852},
{"learn":[3.940251541],"iteration":497,"passed_time":0.1804823973,"remaining_time":0.1819320551},
{"learn":[3.939011019],"iteration":498,"passed_time":0.1807155686,"remaining_time":0.1814398795},
{"learn":[3.938760512],"iteration":499,"passed_time":0.1809501566,"remaining_time":0.1809501566},
{"learn":[3.934522727],"iteration":500,"passed_time":0.1811834529,"remaining_time":0.1804601657},
{"learn":[3.930091193],"iteration":501,"passed_time":0.1814129159,"remaining_time":0.1799673946},
{"learn":[3.927671752],"iteration":502,"passed_time":0.1816322536,"remaining_time":0.1794656661},
{"learn":[3.927280041],"iteration":503,"passed_time":0.1818570081,"remaining_time":0.1789703889},
{"learn":[3.925987561],"iteration":504,"passed_time":0.1820665123,"remaining_time":0.1784612348},
{"learn":[3.921645957],"iteration":505,"passed_time":0.1823041837,"remaining_time":0.1779807643},
{"learn":[3.920333743],"iteration":506,"passed_time":0.1825375217,"remaining_time":0.1774970378},
{"learn":[3.918659461],"iteration":507,"passed_time":0.1827681513,"remaining_time":0.1770116741},
{"learn":[3.916124385],"iteration":508,"passed_time":0.183005531,"remaining_time":0.1765338226},
{"learn":[3.913849268],"iteration":509,"passed_time":0.1832084517,"remaining_time":0.1760238066},
{"learn":[3.912826119],"iteration":510,"passed_time":0.1834457481,"remaining_time":0.1755478881},
{"learn":[3.910034145],"iteration":511,"passed_time":0.1837066284,"remaining_time":0.1750953802},
{"learn":[3.90792379],"iteration":512,"passed_time":0.1839625501,"remaining_time":0.1746389121},
{"learn":[3.907823851],"iteration":513,"passed_time":0.1841920547,"remaining_time":0.1741582463},
{"learn":[3.904527401],"iteration":514,"passed_time":0.184422351,"remaining_time":0.1736793014},
{"learn":[3.903378283],"iteration":515,"passed_time":0.1846468555,"remaining_time":0.1731958877},
{"learn":[3.902170135],"iteration":516,"passed_time":0.1848576097,"remaining_time":0.1727006295},
{"learn":[3.899435429],"iteration":517,"passed_time":0.1850973228,"remaining_time":0.1722334162},
{"learn":[3.897497505],"iteration":518,"passed_time":0.185308952,"remaining_time":0.1717410519},
{"learn":[3.896426119],"iteration":519,"passed_time":0.1855275397,"remaining_time":0.1712561905},
{"learn":[3.896044669],"iteration":520,"passed_time":0.1857403773,"remaining_time":0.1707670648},
{"learn":[3.892795942],"iteration":521,"passed_time":0.185990049,"remaining_time":0.1703127268},
{"learn":[3.892413888],"iteration":522,"passed_time":0.1862250537,"remaining_time":0.1698457946},
{"learn":[3.891738985],"iteration":523,"passed_time":0.186439558,"remaining_time":0.1693611252},
{"learn":[3.88822057],"iteration":524,"passed_time":0.1866804378,"remaining_time":0.1689013485},
{"learn":[3.883837053],"iteration":525,"passed_time":0.186908734,"remaining_time":0.1684310645},
{"learn":[3.881769742],"iteration":526,"passed_time":0.187140447,"remaining_time":0.1679647655},
{"learn":[3.880356898],"iteration":527,"passed_time":0.1873484094,"remaining_time":0.1674781236},
{"learn":[3.879250273],"iteration":528,"passed_time":0.1875928727,"remaining_time":0.1670250341},
{"learn":[3.877174493],"iteration":529,"passed_time":0.1878178772,"remaining_time":0.166555476},
{"learn":[3.875854201],"iteration":530,"passed_time":0.1880421316,"remaining_time":0.1660861765},
{"learn":[3.873189396],"iteration":531,"passed_time":0.1882705529,"remaining_time":0.1656214638},
{"learn":[3.871583368],"iteration":532,"passed_time":0.1884956407,"remaining_time":0.1651547171},
{"learn":[3.869622679],"iteration":533,"passed_time":0.1887854798,"remaining_time":0.1647453813},
{"learn":[3.866860164],"iteration":534,"passed_time":0.1889978591,"remaining_time":0.1642691672},
{"learn":[3.864498444],"iteration":535,"passed_time":0.1892281553,"remaining_time":0.1638094479},
{"learn":[3.861416322],"iteration":536,"passed_time":0.1894628684,"remaining_time":0.1633543911},
{"learn":[3.860265769],"iteration":537,"passed_time":0.1896862895,"remaining_time":0.1628904568},
{"learn":[3.859328725],"iteration":538,"passed_time":0.1899015854,"remaining_time":0.1624204655},
{"learn":[3.858521278],"iteration":539,"passed_time":0.1901305484,"remaining_time":0.1619630597},
{"learn":[3.85599111],"iteration":540,"passed_time":0.1903358441,"remaining_time":0.1614864186},
{"learn":[3.852379816],"iteration":541,"passed_time":0.190579974,"remaining_time":0.1610435943},
{"learn":[3.851327537],"iteration":542,"passed_time":0.1907879782,"remaining_time":0.1605710976},
{"learn":[3.847854898],"iteration":543,"passed_time":0.1910216912,"remaining_time":0.1601211235},
{"learn":[3.847083414],"iteration":544,"passed_time":0.1912821547,"remaining_time":0.1596942759},
{"learn":[3.845397429],"iteration":545,"passed_time":0.1914854088,"remaining_time":0.1592204681},
{"learn":[3.841933528],"iteration":546,"passed_time":0.1917034964,"remaining_time":0.158759934},
{"learn":[3.840996474],"iteration":547,"passed_time":0.1919470013,"remaining_time":0.1583212493},
{"learn":[3.838355966],"iteration":548,"passed_time":0.1921704641,"remaining_time":0.1578668111},
{"learn":[3.83342799],"iteration":549,"passed_time":0.1924025521,"remaining_time":0.1574202699},
{"learn":[3.828161535],"iteration":550,"passed_time":0.1926433486,"remaining_time":0.1569816035},
{"learn":[3.823502399],"iteration":551,"passed_time":0.192883895,"remaining_time":0.156543451},
{"learn":[3.820068862],"iteration":552,"passed_time":0.1932539441,"remaining_time":0.1562106926},
{"learn":[3.817951642],"iteration":553,"passed_time":0.1935840757,"remaining_time":0.1558456638},
{"learn":[3.815785958],"iteration":554,"passed_time":0.1938531644,"remaining_time":0.1554318165},
{"learn":[3.81503012],"iteration":555,"passed_time":0.1941762125,"remaining_time":0.1550615798},
{"learn":[3.813529315],"iteration":556,"passed_time":0.1944481346,"remaining_time":0.1546508503},
{"learn":[3.808881326],"iteration":557,"passed_time":0.1947013063,"remaining_time":0.154225766},
{"learn":[3.808740434],"iteration":558,"passed_time":0.1950424382,"remaining_time":0.1538706891},
{"learn":[3.80714352],"iteration":559,"passed_time":0.1953456525,"remaining_time":0.1534858699},
{"learn":[3.80573346],"iteration":560,"passed_time":0.1955872824,"remaining_time":0.1530531497},
{"learn":[3.803370052],"iteration":561,"passed_time":0.1958290789,"remaining_time":0.1526212394},
{"learn":[3.803215211],"iteration":562,"passed_time":0.1960913341,"remaining_time":0.1522058846},
{"learn":[3.801309667],"iteration":563,"passed_time":0.1963195053,"remaining_time":0.151764724},
{"learn":[3.800003847],"iteration":564,"passed_time":0.1966751374,"remaining_time":0.1514224509},
{"learn":[3.798026138],"iteration":565,"passed_time":0.1970501033,"remaining_time":0.1510949555},
{"learn":[3.794745847],"iteration":566,"passed_time":0.1974632782,"remaining_time":0.1507964717},
{"learn":[3.794312041],"iteration":567,"passed_time":0.1977847013,"remaining_time":0.150427801},
{"learn":[3.792205926],"iteration":568,"passed_time":0.1980878323,"remaining_time":0.1500454407},
{"learn":[3.788991061],"iteration":569,"passed_time":0.1983442958,"remaining_time":0.149628153},
{"learn":[3.787391572],"iteration":570,"passed_time":0.1985914674,"remaining_time":0.1492044475},
{"learn":[3.7826445],"iteration":571,"passed_time":0.198822597,"remaining_time":0.1487693558},
{"learn":[3.781700331],"iteration":572,"passed_time":0.1990423514,"remaining_time":0.1483264992},
{"learn":[3.780045374],"iteration":573,"passed_time":0.1992720643,"remaining_time":0.1478918108},
{"learn":[3.775462644],"iteration":574,"passed_time":0.1994865686,"remaining_time":0.1474465942},
{"learn":[3.773711943],"iteration":575,"passed_time":0.1997544073,"remaining_time":0.1470414387},
{"learn":[3.772415806],"iteration":576,"passed_time":0.2000037456,"remaining_time":0.1466231965},
{"learn":[3.770170875],"iteration":577,"passed_time":0.2002040829,"remaining_time":0.146169763},
{"learn":[3.765166479],"iteration":578,"passed_time":0.2004122538,"remaining_time":0.1457228995},
{"learn":[3.763976102],"iteration":579,"passed_time":0.2007302184,"remaining_time":0.1453563651},
{"learn":[3.760761708],"iteration":580,"passed_time":0.2009444727,"remaining_time":0.1449152049},
{"learn":[3.758155662],"iteration":581,"passed_time":0.2011961444,"remaining_time":0.1445016982},
{"learn":[3.756844548],"iteration":582,"passed_time":0.2014479411,"remaining_time":0.1440888361},
{"learn":[3.753098923],"iteration":583,"passed_time":0.2016943627,"remaining_time":0.1436726967},
{"learn":[3.751618946],"iteration":584,"passed_time":0.2019295757,"remaining_time":0.1432491862},
{"learn":[3.751398464],"iteration":585,"passed_time":0.202176789,"remaining_time":0.1428347963},
{"learn":[3.749920103],"iteration":586,"passed_time":0.202458878,"remaining_time":0.1424455138},
{"learn":[3.748237465],"iteration":587,"passed_time":0.2027723842,"remaining_time":0.1420786094},
{"learn":[3.746021536],"iteration":588,"passed_time":0.2030049306,"remaining_time":0.141655393},
{"learn":[3.74417648],"iteration":589,"passed_time":0.203245602,"remaining_time":0.1412384692},
{"learn":[3.738788389],"iteration":590,"passed_time":0.2034782733,"remaining_time":0.1408166054},
{"learn":[3.736021611],"iteration":591,"passed_time":0.2037097363,"remaining_time":0.140394548},
{"learn":[3.734546151],"iteration":592,"passed_time":0.203926199,"remaining_time":0.1399628381},
{"learn":[3.733527479],"iteration":593,"passed_time":0.2041581203,"remaining_time":0.1395424189},
{"learn":[3.733026392],"iteration":594,"passed_time":0.2043591243,"remaining_time":0.1391015888},
{"learn":[3.730314752],"iteration":595,"passed_time":0.2046306297,"remaining_time":0.138709353},
{"learn":[3.727342596],"iteration":596,"passed_time":0.2049518028,"remaining_time":0.1383510495},
{"learn":[3.725459604],"iteration":597,"passed_time":0.205196891,"remaining_time":0.1379417227},
{"learn":[3.723158842],"iteration":598,"passed_time":0.2054344374,"remaining_time":0.1375278955},
{"learn":[3.722362756],"iteration":599,"passed_time":0.2056709422,"remaining_time":0.1371139614},
{"learn":[3.721443615],"iteration":600,"passed_time":0.2058866548,"remaining_time":0.1366868141},
{"learn":[3.720743486],"iteration":601,"passed_time":0.2060922006,"remaining_time":0.1362536476},
{"learn":[3.720215334],"iteration":602,"passed_time":0.2063185801,"remaining_time":0.1358349524},
{"learn":[3.719436563],"iteration":603,"passed_time":0.2065428762,"remaining_time":0.1354155281},
{"learn":[3.715046574],"iteration":604,"passed_time":0.2067687141,"remaining_time":0.1349977555},
{"learn":[3.71443396],"iteration":605,"passed_time":0.2069929686,"remaining_time":0.1345795868},
{"learn":[3.712938941],"iteration":606,"passed_time":0.2072340567,"remaining_time":0.134172956},
{"learn":[3.712814764],"iteration":607,"passed_time":0.2075710218,"remaining_time":0.1338286851},
{"learn":[3.71235348],"iteration":608,"passed_time":0.2078111516,"remaining_time":0.1334222664},
{"learn":[3.711223749],"iteration":609,"passed_time":0.2080688651,"remaining_time":0.133027635},
{"learn":[3.710755648],"iteration":610,"passed_time":0.2083992467,"remaining_time":0.1326797168},
{"learn":[3.708668039],"iteration":611,"passed_time":0.2086219178,"remaining_time":0.1322635688},
{"learn":[3.705623591],"iteration":612,"passed_time":0.2088557558,"remaining_time":0.1318551019},
{"learn":[3.704045802],"iteration":613,"passed_time":0.2091073025,"remaining_time":0.1314583367},
{"learn":[3.699915209],"iteration":614,"passed_time":0.2093803079,"remaining_time":0.1310754773},
{"learn":[3.696182221],"iteration":615,"passed_time":0.2096069791,"remaining_time":0.1306640909},
{"learn":[3.694263278],"iteration":616,"passed_time":0.2098296502,"remaining_time":0.1302508202},
{"learn":[3.693810229],"iteration":617,"passed_time":0.2100654049,"remaining_time":0.1298462535},
{"learn":[3.690900932],"iteration":618,"passed_time":0.2103374104,"remaining_time":0.129464545},
{"learn":[3.688020895],"iteration":619,"passed_time":0.2105716651,"remaining_time":0.1290600528},
{"learn":[3.685491894],"iteration":620,"passed_time":0.2108761711,"remaining_time":0.1286989837},
{"learn":[3.684328128],"iteration":621,"passed_time":0.2112485119,"remaining_time":0.1283793207},
{"learn":[3.680640153],"iteration":622,"passed_time":0.2116065607,"remaining_time":0.1280508401},
{"learn":[3.678932783],"iteration":623,"passed_time":0.211919567,"remaining_time":0.1276951237},
{"learn":[3.674167041],"iteration":624,"passed_time":0.2122227814,"remaining_time":0.1273336688},
{"learn":[3.672200976],"iteration":625,"passed_time":0.2125181623,"remaining_time":0.12696772},
{"learn":[3.670606604],"iteration":626,"passed_time":0.2127734174,"remaining_time":0.1265781255},
{"learn":[3.665506042],"iteration":627,"passed_time":0.2130105054,"remaining_time":0.1261781975},
{"learn":[3.664214007],"iteration":628,"passed_time":0.2132547187,"remaining_time":0.1257829899},
{"learn":[3.66261643],"iteration":629,"passed_time":0.2135296825,"remaining_time":0.1254063215},
{"learn":[3.662118449],"iteration":630,"passed_time":0.2138360636,"remaining_time":0.1250483478},
{"learn":[3.660871366],"iteration":631,"passed_time":0.2140477762,"remaining_time":0.124635414},
{"learn":[3.656695243],"iteration":632,"passed_time":0.2142776974,"remaining_time":0.1242336729},
{"learn":[3.654497801],"iteration":633,"passed_time":0.2145152022,"remaining_time":0.1238368517},
{"learn":[3.654189134],"iteration":634,"passed_time":0.2147400817,"remaining_time":0.1234332753},
{"learn":[3.653957699],"iteration":635,"passed_time":0.2149536693,"remaining_time":0.1230237981},
{"learn":[3.651920725],"iteration":636,"passed_time":0.2151609651,"remaining_time":0.1226113506},
{"learn":[3.65106705],"iteration":637,"passed_time":0.2153894696,"remaining_time":0.12221158},
{"learn":[3.650612844],"iteration":638,"passed_time":0.2156086823,"remaining_time":0.121807096},
{"learn":[3.649884732],"iteration":639,"passed_time":0.2158471454,"remaining_time":0.1214140193},
{"learn":[3.646276182],"iteration":640,"passed_time":0.2160738166,"remaining_time":0.1210148209},
{"learn":[3.645808194],"iteration":641,"passed_time":0.2163011545,"remaining_time":0.1206165316},
{"learn":[3.645042989],"iteration":642,"passed_time":0.2165253257,"remaining_time":0.120217016},
{"learn":[3.639864499],"iteration":643,"passed_time":0.2167522052,"remaining_time":0.119819542},
{"learn":[3.637318478],"iteration":644,"passed_time":0.2169654595,"remaining_time":0.1194150978},
{"learn":[3.636344905],"iteration":645,"passed_time":0.2171837138,"remaining_time":0.1190139856},
{"learn":[3.634754643],"iteration":646,"passed_time":0.2174092183,"remaining_time":0.1186173942},
{"learn":[3.630724975],"iteration":647,"passed_time":0.2176551399,"remaining_time":0.1182324217},
{"learn":[3.629408252],"iteration":648,"passed_time":0.2178961447,"remaining_time":0.1178452185},
{"learn":[3.62790646],"iteration":649,"passed_time":0.2181197742,"remaining_time":0.1174491092},
{"learn":[3.627388973],"iteration":650,"passed_time":0.218429197,"remaining_time":0.1170995234},
{"learn":[3.625163557],"iteration":651,"passed_time":0.2187495368,"remaining_time":0.1167558877},
{"learn":[3.623701985],"iteration":652,"passed_time":0.2189855831,"remaining_time":0.1163675304},
{"learn":[3.622342639],"iteration":653,"passed_time":0.2192109626,"remaining_time":0.1159739955},
{"learn":[3.621130639],"iteration":654,"passed_time":0.2194580926,"remaining_time":0.1155924304},
{"learn":[3.619125665],"iteration":655,"passed_time":0.2197120143,"remaining_time":0.1152148368},
{"learn":[3.618878783],"iteration":656,"passed_time":0.2199441856,"remaining_time":0.1148262643},
{"learn":[3.616207429],"iteration":657,"passed_time":0.2202823174,"remaining_time":0.114493241},
{"learn":[3.61206486],"iteration":658,"passed_time":0.2205123636,"remaining_time":0.1141042731},
{"learn":[3.611955873],"iteration":659,"passed_time":0.220731993,"remaining_time":0.1137104207},
{"learn":[3.610713743],"iteration":660,"passed_time":0.2209632477,"remaining_time":0.1133230574},
{"learn":[3.610044025],"iteration":661,"passed_time":0.2211827937,"remaining_time":0.1129301877},
{"learn":[3.607342669],"iteration":662,"passed_time":0.2213943396,"remaining_time":0.1125337744},
{"learn":[3.602510618],"iteration":663,"passed_time":0.2216425529,"remaining_time":0.1121564725},
{"learn":[3.600492392],"iteration":664,"passed_time":0.2218693074,"remaining_time":0.1117687489},
{"learn":[3.597171065],"iteration":665,"passed_time":0.2220946453,"remaining_time":0.1113807981},
{"learn":[3.594358798],"iteration":666,"passed_time":0.2223239415,"remaining_time":0.1109953111},
{"learn":[3.593945251],"iteration":667,"passed_time":0.2225462376,"remaining_time":0.1106068127},
{"learn":[3.593607748],"iteration":668,"passed_time":0.2227819923,"remaining_time":0.11022547},
{"learn":[3.592238714],"iteration":669,"passed_time":0.2231261242,"remaining_time":0.1098979418},
{"learn":[3.590144654],"iteration":670,"passed_time":0.2234413388,"remaining_time":0.1095561855},
{"learn":[3.587151536],"iteration":671,"passed_time":0.2237297613,"remaining_time":0.1092014311},
{"learn":[3.586070865],"iteration":672,"passed_time":0.2239755578,"remaining_time":0.1088261626},
{"learn":[3.585102746],"iteration":673,"passed_time":0.2243252732,"remaining_time":0.1085015416},
{"learn":[3.584362847],"iteration":674,"passed_time":0.2246659466,"remaining_time":0.1081724928},
{"learn":[3.581407561],"iteration":675,"passed_time":0.225017162,"remaining_time":0.1078484622},
{"learn":[3.57919422],"iteration":676,"passed_time":0.2253861277,"remaining_time":0.1075328201},
{"learn":[3.577632204],"iteration":677,"passed_time":0.2257540517,"remaining_time":0.107216526},
{"learn":[3.573911195],"iteration":678,"passed_time":0.2259808479,"remaining_time":0.1068333611},
{"learn":[3.573408216],"iteration":679,"passed_time":0.226318813,"remaining_time":0.1065029708},
{"learn":[3.571076482],"iteration":680,"passed_time":0.2266460695,"remaining_time":0.1061675421},
{"learn":[3.568177107],"iteration":681,"passed_time":0.2268860743,"remaining_time":0.105791454},
{"learn":[3.564824621],"iteration":682,"passed_time":0.2271637465,"remaining_time":0.1054332469},
{"learn":[3.562475026],"iteration":683,"passed_time":0.2274704193,"remaining_time":0.1050886733},
{"learn":[3.561226889],"iteration":684,"passed_time":0.2278352183,"remaining_time":0.1047709398},
{"learn":[3.559383467],"iteration":685,"passed_time":0.2281077654,"remaining_time":0.104410843},
{"learn":[3.555209766],"iteration":686,"passed_time":0.228340895,"remaining_time":0.1040330424},
{"learn":[3.55345383],"iteration":687,"passed_time":0.2285823582,"remaining_time":0.1036594415},
{"learn":[3.552300968],"iteration":688,"passed_time":0.2288338632,"remaining_time":0.1032907568},
{"learn":[3.551253986],"iteration":689,"passed_time":0.2290967018,"remaining_time":0.1029275037},
{"learn":[3.549807725],"iteration":690,"passed_time":0.2293278731,"remaining_time":0.1025503803},
{"learn":[3.547992926],"iteration":691,"passed_time":0.2296001702,"remaining_time":0.1021919833},
{"learn":[3.545438607],"iteration":692,"passed_time":0.2299480938,"remaining_time":0.1018673374},
{"learn":[3.543313763],"iteration":693,"passed_time":0.2303266847,"remaining_time":0.1015561463},
{"learn":[3.542962896],"iteration":694,"passed_time":0.2307995275,"remaining_time":0.1012861236},
{"learn":[3.539800465],"iteration":695,"passed_time":0.2312063273,"remaining_time":0.1009866717},
{"learn":[3.53953187],"iteration":696,"passed_time":0.2315881682,"remaining_time":0.1006760617},
{"learn":[3.536332425],"iteration":697,"passed_time":0.2318877576,"remaining_time":0.1003296602},
{"learn":[3.534993327],"iteration":698,"passed_time":0.2321068036,"remaining_time":0.09994870942},
{"learn":[3.531637011],"iteration":699,"passed_time":0.2323558086,"remaining_time":0.09958106082},
{"learn":[3.531040284],"iteration":700,"passed_time":0.2325811464,"remaining_time":0.09920365589},
{"learn":[3.529973872],"iteration":701,"passed_time":0.2327964424,"remaining_time":0.09882242141},
{"learn":[3.527325183],"iteration":702,"passed_time":0.2330582393,"remaining_time":0.09846130451},
{"learn":[3.527200815],"iteration":703,"passed_time":0.2332729936,"remaining_time":0.09808069048},
{"learn":[3.523459911],"iteration":704,"passed_time":0.2335105817,"remaining_time":0.09771010154},
{"learn":[3.522729934],"iteration":705,"passed_time":0.2337272526,"remaining_time":0.09733117887},
{"learn":[3.522260582],"iteration":706,"passed_time":0.2339886745,"remaining_time":0.09697126116},
{"learn":[3.518641591],"iteration":707,"passed_time":0.2342200958,"remaining_time":0.09659924856},
{"learn":[3.516856405],"iteration":708,"passed_time":0.2344313917,"remaining_time":0.09621937234},
{"learn":[3.515083413],"iteration":709,"passed_time":0.2347933156,"remaining_time":0.09590149511},
{"learn":[3.514671214],"iteration":710,"passed_time":0.2350172784,"remaining_time":0.09552741697},
{"learn":[3.512617621],"iteration":711,"passed_time":0.2352579499,"remaining_time":0.09516051906},
{"learn":[3.510747971],"iteration":712,"passed_time":0.2354937463,"remaining_time":0.09479201288},
{"learn":[3.508149266],"iteration":713,"passed_time":0.2357220842,"remaining_time":0.09442089086},
{"learn":[3.504557165],"iteration":714,"passed_time":0.2359457136,"remaining_time":0.09404829145},
{"learn":[3.501367208],"iteration":715,"passed_time":0.2361709681,"remaining_time":0.09367675272},
{"learn":[3.497593362],"iteration":716,"passed_time":0.2364165147,"remaining_time":0.09331363133},
{"learn":[3.496291169],"iteration":717,"passed_time":0.2366503527,"remaining_time":0.09294623881},
{"learn":[3.49330374],"iteration":718,"passed_time":0.2368767322,"remaining_time":0.09257630286},
{"learn":[3.490044385],"iteration":719,"passed_time":0.2370941949,"remaining_time":0.09220329802},
{"learn":[3.488891789],"iteration":720,"passed_time":0.2373203244,"remaining_time":0.09183407839},
{"learn":[3.486869081],"iteration":721,"passed_time":0.2375606626,"remaining_time":0.09147072603},
{"learn":[3.486303638],"iteration":722,"passed_time":0.2377987923,"remaining_time":0.09110686787},
{"learn":[3.486035862],"iteration":723,"passed_time":0.2380296303,"remaining_time":0.09074057728},
{"learn":[3.482668951],"iteration":724,"passed_time":0.2383010107,"remaining_time":0.09039003854},
{"learn":[3.47820549],"iteration":725,"passed_time":0.2387873121,"remaining_time":0.09012083128},
{"learn":[3.474392283],"iteration":726,"passed_time":0.2391250272,"remaining_time":0.08979523028},
{"learn":[3.472268163],"iteration":727,"passed_time":0.2394904094,"remaining_time":0.0894799332},
{"learn":[3.471209164],"iteration":728,"passed_time":0.2397264558,"remaining_time":0.08911641911},
{"learn":[3.470049971],"iteration":729,"passed_time":0.2399507103,"remaining_time":0.08874889286},
{"learn":[3.469078654],"iteration":730,"passed_time":0.2402504246,"remaining_time":0.08840952699},
{"learn":[3.468643292],"iteration":731,"passed_time":0.2405828896,"remaining_time":0.08808226013},
{"learn":[3.468134848],"iteration":732,"passed_time":0.2408231861,"remaining_time":0.08772140611},
{"learn":[3.467820182],"iteration":733,"passed_time":0.2410622742,"remaining_time":0.08736044269},
{"learn":[3.465776156],"iteration":734,"passed_time":0.2413018623,"remaining_time":0.08699999117},
{"learn":[3.463037608],"iteration":735,"passed_time":0.2415253668,"remaining_time":0.08663409895},
{"learn":[3.45965637],"iteration":736,"passed_time":0.2417577464,"remaining_time":0.08627176025},
{"learn":[3.457275091],"iteration":737,"passed_time":0.2419902511,"remaining_time":0.08590981813},
{"learn":[3.455522955],"iteration":738,"passed_time":0.2422088388,"remaining_time":0.08554331112},
{"learn":[3.451270508],"iteration":739,"passed_time":0.2424590104,"remaining_time":0.08518830096},
{"learn":[3.450978947],"iteration":740,"passed_time":0.2426949735,"remaining_time":0.08482860746},
{"learn":[3.450608492],"iteration":741,"passed_time":0.2429308532,"remaining_time":0.08446921849},
{"learn":[3.448122004],"iteration":742,"passed_time":0.243306944,"remaining_time":0.08415866032},
{"learn":[3.445646714],"iteration":743,"passed_time":0.2436469092,"remaining_time":0.08383549562},
{"learn":[3.44411263],"iteration":744,"passed_time":0.2439786241,"remaining_time":0.08350946194},
{"learn":[3.443264164],"iteration":745,"passed_time":0.2443769237,"remaining_time":0.08320608395},
{"learn":[3.439521363],"iteration":746,"passed_time":0.2446701379,"remaining_time":0.08286686064},
{"learn":[3.436809225],"iteration":747,"passed_time":0.2449628938,"remaining_time":0.08252760592},
{"learn":[3.435509465],"iteration":748,"passed_time":0.2451781897,"remaining_time":0.08216251752},
{"learn":[3.434450277],"iteration":749,"passed_time":0.2453918607,"remaining_time":0.08179728689},
{"learn":[3.431786753],"iteration":750,"passed_time":0.2456066566,"remaining_time":0.08143283289},
{"learn":[3.430150302],"iteration":751,"passed_time":0.2458082857,"remaining_time":0.08106443463},
{"learn":[3.42696281],"iteration":752,"passed_time":0.2460237066,"remaining_time":0.08070100337},
{"learn":[3.426870334],"iteration":753,"passed_time":0.2462406276,"remaining_time":0.08033845411},
{"learn":[3.425200309],"iteration":754,"passed_time":0.2464549653,"remaining_time":0.0799754523},
{"learn":[3.423383783],"iteration":755,"passed_time":0.2467415126,"remaining_time":0.07963614958},
{"learn":[3.422752979],"iteration":756,"passed_time":0.246992851,"remaining_time":0.07928568401},
{"learn":[3.420845924],"iteration":757,"passed_time":0.2472091887,"remaining_time":0.07892430561},
{"learn":[3.418917862],"iteration":758,"passed_time":0.2474243596,"remaining_time":0.07856293896},
{"learn":[3.417095735],"iteration":759,"passed_time":0.247641989,"remaining_time":0.07820273336},
{"learn":[3.414391848],"iteration":760,"passed_time":0.2478833271,"remaining_time":0.07785034846},
{"learn":[3.41426711],"iteration":761,"passed_time":0.2481200818,"remaining_time":0.07749682346},
{"learn":[3.411976013],"iteration":762,"passed_time":0.2483522115,"remaining_time":0.07714216792},
{"learn":[3.408614844],"iteration":763,"passed_time":0.2485836328,"remaining_time":0.07678761431},
{"learn":[3.407906721],"iteration":764,"passed_time":0.248795262,"remaining_time":0.07642730271},
{"learn":[3.407494015],"iteration":765,"passed_time":0.2490418086,"remaining_time":0.07607804597},
{"learn":[3.406287128],"iteration":766,"passed_time":0.2492538128,"remaining_time":0.07571856374},
{"learn":[3.404600442],"iteration":767,"passed_time":0.2494823174,"remaining_time":0.07536445005},
{"learn":[3.404012662],"iteration":768,"passed_time":0.2496942383,"remaining_time":0.07500568147},
{"learn":[3.400398762],"iteration":769,"passed_time":0.2499173678,"remaining_time":0.07465064232},
{"learn":[3.399737714],"iteration":770,"passed_time":0.2501393722,"remaining_time":0.0742956112},
{"learn":[3.399185251],"iteration":771,"passed_time":0.2504373781,"remaining_time":0.07396337075},
{"learn":[3.397245411],"iteration":772,"passed_time":0.2506577575,"remaining_time":0.07360842298},
{"learn":[3.396229831],"iteration":773,"passed_time":0.2508673034,"remaining_time":0.07325065965},
{"learn":[3.394002836],"iteration":774,"passed_time":0.2510928912,"remaining_time":0.07289793617},
{"learn":[3.389617243],"iteration":775,"passed_time":0.2513089372,"remaining_time":0.072542786},
{"learn":[3.385426488],"iteration":776,"passed_time":0.2515419835,"remaining_time":0.07219287301},
{"learn":[3.385072258],"iteration":777,"passed_time":0.2517915719,"remaining_time":0.07184798066},
{"learn":[3.383842366],"iteration":778,"passed_time":0.2521241618,"remaining_time":0.07152688032},
{"learn":[3.380110746],"iteration":779,"passed_time":0.252364625,"remaining_time":0.07117976602},
{"learn":[3.378595218],"iteration":780,"passed_time":0.2525791293,"remaining_time":0.07082564572},
{"learn":[3.377371219],"iteration":781,"passed_time":0.2528424679,"remaining_time":0.07048549615},
{"learn":[3.375814782],"iteration":782,"passed_time":0.2530630139,"remaining_time":0.0701336833},
{"learn":[3.374195887],"iteration":783,"passed_time":0.2533134356,"remaining_time":0.06979043634},
{"learn":[3.373704309],"iteration":784,"passed_time":0.253549982,"remaining_time":0.06944362564},
{"learn":[3.372971757],"iteration":785,"passed_time":0.2537728614,"remaining_time":0.06909337449},
{"learn":[3.371565136],"iteration":786,"passed_time":0.254050242,"remaining_time":0.06875819764},
{"learn":[3.3700309],"iteration":787,"passed_time":0.254319164,"remaining_time":0.06842089184},
{"learn":[3.368186663],"iteration":788,"passed_time":0.254601253,"remaining_time":0.06808728059},
{"learn":[3.366710398],"iteration":789,"passed_time":0.2548728834,"remaining_time":0.06775101964},
{"learn":[3.364598042],"iteration":790,"passed_time":0.2552295989,"remaining_time":0.0674374035},
{"learn":[3.36348442],"iteration":791,"passed_time":0.2554778122,"remaining_time":0.067095183},
{"learn":[3.362001759],"iteration":792,"passed_time":0.2557359007,"remaining_time":0.06675577735},
{"learn":[3.361580401],"iteration":793,"passed_time":0.2559673636,"remaining_time":0.06640966865},
{"learn":[3.359543675],"iteration":794,"passed_time":0.2562115768,"remaining_time":0.06606713616},
{"learn":[3.35766119],"iteration":795,"passed_time":0.2564426231,"remaining_time":0.06572147628},
{"learn":[3.354592969],"iteration":796,"passed_time":0.2566727944,"remaining_time":0.06537588113},
{"learn":[3.350985986],"iteration":797,"passed_time":0.2569298412,"remaining_time":0.06503737834},
{"learn":[3.349589624],"iteration":798,"passed_time":0.2571771378,"remaining_time":0.06469662665},
{"learn":[3.349110856],"iteration":799,"passed_time":0.2574167259,"remaining_time":0.06435418148},
{"learn":[3.345315441],"iteration":800,"passed_time":0.2576933564,"remaining_time":0.06402119592},
{"learn":[3.34397474],"iteration":801,"passed_time":0.2580510302,"remaining_time":0.06370835909},
{"learn":[3.343800902],"iteration":802,"passed_time":0.2583596197,"remaining_time":0.06338336873},
{"learn":[3.342329465],"iteration":803,"passed_time":0.2587307105,"remaining_time":0.06307365579},
{"learn":[3.34220347],"iteration":804,"passed_time":0.2591126765,"remaining_time":0.06276642473},
{"learn":[3.341279219],"iteration":805,"passed_time":0.2594442247,"remaining_time":0.06244687295},
{"learn":[3.337329521],"iteration":806,"passed_time":0.259805232,"remaining_time":0.06213433676},
{"learn":[3.336708453],"iteration":807,"passed_time":0.2601130298,"remaining_time":0.06180903678},
{"learn":[3.333252703],"iteration":808,"passed_time":0.2604519949,"remaining_time":0.06149113847},
{"learn":[3.332186769],"iteration":809,"passed_time":0.2607746263,"remaining_time":0.06116935679},
{"learn":[3.330594851],"iteration":810,"passed_time":0.261008131,"remaining_time":0.06082680241},
{"learn":[3.327867442],"iteration":811,"passed_time":0.2612188435,"remaining_time":0.06047923964},
{"learn":[3.327563111],"iteration":812,"passed_time":0.2614401813,"remaining_time":0.06013445744},
{"learn":[3.326308994],"iteration":813,"passed_time":0.2616563523,"remaining_time":0.05978879794},
{"learn":[3.326249879],"iteration":814,"passed_time":0.261892482,"remaining_time":0.05944798671},
{"learn":[3.322336238],"iteration":815,"passed_time":0.2621204032,"remaining_time":0.05910558112},
{"learn":[3.320491154],"iteration":816,"passed_time":0.2623716582,"remaining_time":0.05876868232},
{"learn":[3.320434271],"iteration":817,"passed_time":0.2626049546,"remaining_time":0.05842799722},
{"learn":[3.319609638],"iteration":818,"passed_time":0.2628313341,"remaining_time":0.05808604575},
{"learn":[3.316182682],"iteration":819,"passed_time":0.2630327131,"remaining_time":0.05773888824},
{"learn":[3.313126612],"iteration":820,"passed_time":0.2632706762,"remaining_time":0.05740006217},
{"learn":[3.311222803],"iteration":821,"passed_time":0.263493264,"remaining_time":0.05705815205},
{"learn":[3.309627335],"iteration":822,"passed_time":0.2637114767,"remaining_time":0.05671559097},
{"learn":[3.307974895],"iteration":823,"passed_time":0.2640094409,"remaining_time":0.05639036603},
{"learn":[3.307321505],"iteration":824,"passed_time":0.2642488624,"remaining_time":0.05605278899},
{"learn":[3.306759087],"iteration":825,"passed_time":0.2644749919,"remaining_time":0.05571264963},
{"learn":[3.30484037],"iteration":826,"passed_time":0.2647522891,"remaining_time":0.05538348974},
{"learn":[3.30201994],"iteration":827,"passed_time":0.2651002544,"remaining_time":0.05506913497},
{"learn":[3.299302297],"iteration":828,"passed_time":0.2653368008,"remaining_time":0.05473171645},
{"learn":[3.298132671],"iteration":829,"passed_time":0.2655646387,"remaining_time":0.05439275732},
{"learn":[3.296976183],"iteration":830,"passed_time":0.2657940183,"remaining_time":0.05405437917},
{"learn":[3.293144745],"iteration":831,"passed_time":0.2660235645,"remaining_time":0.05371629668},
{"learn":[3.290284404],"iteration":832,"passed_time":0.2662632776,"remaining_time":0.05338051304},
{"learn":[3.288285745],"iteration":833,"passed_time":0.2664912405,"remaining_time":0.05304262102},
{"learn":[3.286662667],"iteration":834,"passed_time":0.2667432872,"remaining_time":0.05270975137},
{"learn":[3.285692682],"iteration":835,"passed_time":0.266984417,"remaining_time":0.05237493349},
{"learn":[3.284565611],"iteration":836,"passed_time":0.2672065465,"remaining_time":0.05203663928},
{"learn":[3.283897383],"iteration":837,"passed_time":0.2674227175,"remaining_time":0.05169747044},
{"learn":[3.280712855],"iteration":838,"passed_time":0.2676195964,"remaining_time":0.05135489275},
{"learn":[3.280468341],"iteration":839,"passed_time":0.2678295589,"remaining_time":0.05101515408},
{"learn":[3.277814895],"iteration":840,"passed_time":0.2680800639,"remaining_time":0.05068338902},
{"learn":[3.276316385],"iteration":841,"passed_time":0.2682985266,"remaining_time":0.05034580429},
{"learn":[3.27557063],"iteration":842,"passed_time":0.2685485733,"remaining_time":0.05001438435},
{"learn":[3.27499628],"iteration":843,"passed_time":0.2687925365,"remaining_time":0.04968203281},
{"learn":[3.273569958],"iteration":844,"passed_time":0.269034208,"remaining_time":0.04934947011},
{"learn":[3.269665595],"iteration":845,"passed_time":0.2692962549,"remaining_time":0.04902083127},
{"learn":[3.267984685],"iteration":846,"passed_time":0.2695608435,"remaining_time":0.04869280881},
{"learn":[3.267702508],"iteration":847,"passed_time":0.2698705164,"remaining_time":0.04837301709},
{"learn":[3.266671924],"iteration":848,"passed_time":0.270271066,"remaining_time":0.04806941222},
{"learn":[3.265359825],"iteration":849,"passed_time":0.2706374067,"remaining_time":0.04775954236},
{"learn":[3.2618983],"iteration":850,"passed_time":0.2710069141,"remaining_time":0.04745009424},
{"learn":[3.260456253],"iteration":851,"passed_time":0.271322587,"remaining_time":0.04713115362},
{"learn":[3.258389147],"iteration":852,"passed_time":0.2715604251,"remaining_time":0.04679880714},
{"learn":[3.258108469],"iteration":853,"passed_time":0.2717903464,"remaining_time":0.04646532854},
{"learn":[3.256424936],"iteration":854,"passed_time":0.2720484765,"remaining_time":0.04613687614},
{"learn":[3.254817983],"iteration":855,"passed_time":0.2723036483,"remaining_time":0.04580809037},
{"learn":[3.253898449],"iteration":856,"passed_time":0.2725414031,"remaining_time":0.04547657017},
{"learn":[3.253023652],"iteration":857,"passed_time":0.2727525739,"remaining_time":0.04514086888},
{"learn":[3.252845542],"iteration":858,"passed_time":0.2729915787,"remaining_time":0.04481002631},
{"learn":[3.252316026],"iteration":859,"passed_time":0.2732697926,"remaining_time":0.04448578019},
{"learn":[3.24975301],"iteration":860,"passed_time":0.2734969222,"remaining_time":0.04415339394},
{"learn":[3.249151075],"iteration":861,"passed_time":0.2737616774,"remaining_time":0.04382727551},
{"learn":[3.246257135],"iteration":862,"passed_time":0.2740317245,"remaining_time":0.04350213935},
{"learn":[3.243826471],"iteration":863,"passed_time":0.2742872296,"remaining_time":0.0431748417},
{"learn":[3.243190653],"iteration":864,"passed_time":0.2745341095,"remaining_time":0.04284636392},
{"learn":[3.24008797],"iteration":865,"passed_time":0.2748458241,"remaining_time":0.04252810673},
{"learn":[3.240036811],"iteration":866,"passed_time":0.2751414967,"remaining_time":0.04220740376},
{"learn":[3.238676314],"iteration":867,"passed_time":0.2754530446,"remaining_time":0.04188917268},
{"learn":[3.237848782],"iteration":868,"passed_time":0.2756785491,"remaining_time":0.04155798611},
{"learn":[3.236405498],"iteration":869,"passed_time":0.2759126371,"remaining_time":0.04122832508},
{"learn":[3.233378068],"iteration":870,"passed_time":0.2761400166,"remaining_time":0.04089788995},
{"learn":[3.233169169],"iteration":871,"passed_time":0.276374813,"remaining_time":0.04056877989},
{"learn":[3.232434885],"iteration":872,"passed_time":0.2766177345,"remaining_time":0.04024106791},
{"learn":[3.229978115],"iteration":873,"passed_time":0.2768568643,"remaining_time":0.03991300332},
{"learn":[3.229648848],"iteration":874,"passed_time":0.277076327,"remaining_time":0.03958233243},
{"learn":[3.227208761],"iteration":875,"passed_time":0.2773060399,"remaining_time":0.03925336638},
{"learn":[3.226258869],"iteration":876,"passed_time":0.2775172525,"remaining_time":0.03892203199},
{"learn":[3.225331995],"iteration":877,"passed_time":0.2777486321,"remaining_time":0.03859377348},
{"learn":[3.221968268],"iteration":878,"passed_time":0.2779820534,"remaining_time":0.03826601646},
{"learn":[3.221166317],"iteration":879,"passed_time":0.2782354752,"remaining_time":0.03794120116},
{"learn":[3.220047503],"iteration":880,"passed_time":0.2784652714,"remaining_time":0.03761335675},
{"learn":[3.21982781],"iteration":881,"passed_time":0.2787091096,"remaining_time":0.0372876133},
{"learn":[3.216693405],"iteration":882,"passed_time":0.2789658231,"remaining_time":0.03696376138},
{"learn":[3.214798761],"iteration":883,"passed_time":0.2791910359,"remaining_time":0.03663592779},
{"learn":[3.214395085],"iteration":884,"passed_time":0.2794221655,"remaining_time":0.03630909496},
{"learn":[3.213470696],"iteration":885,"passed_time":0.2796400032,"remaining_time":0.03598076791},
{"learn":[3.211595017],"iteration":886,"passed_time":0.2798625077,"remaining_time":0.03565328452},
{"learn":[3.210965255],"iteration":887,"passed_time":0.2800967207,"remaining_time":0.03532751432},
{"learn":[3.209413583],"iteration":888,"passed_time":0.2803457673,"remaining_time":0.03500380222},
{"learn":[3.208331683],"iteration":889,"passed_time":0.2806731488,"remaining_time":0.03468993975},
{"learn":[3.207110711],"iteration":890,"passed_time":0.2809234038,"remaining_time":0.03436661169},
{"learn":[3.204519413],"iteration":891,"passed_time":0.2811823257,"remaining_time":0.03404449683},
{"learn":[3.201421296],"iteration":892,"passed_time":0.2814121636,"remaining_time":0.03371903864},
{"learn":[3.200691259],"iteration":893,"passed_time":0.2816340014,"remaining_time":0.0333928458},
{"learn":[3.200485067],"iteration":894,"passed_time":0.2818571308,"remaining_time":0.0330670377},
{"learn":[3.197467568],"iteration":895,"passed_time":0.2820893021,"remaining_time":0.03274250828},
{"learn":[3.195838544],"iteration":896,"passed_time":0.2823271819,"remaining_time":0.03241884028},
{"learn":[3.195671746],"iteration":897,"passed_time":0.2825565615,"remaining_time":0.03209439785},
{"learn":[3.194213094],"iteration":898,"passed_time":0.2827846494,"remaining_time":0.03177002179},
{"learn":[3.192884691],"iteration":899,"passed_time":0.2829977786,"remaining_time":0.03144419762},
{"learn":[3.188364239],"iteration":900,"passed_time":0.2832412835,"remaining_time":0.03112196123},
{"learn":[3.185219478],"iteration":901,"passed_time":0.283481955,"remaining_time":0.03079959156},
{"learn":[3.184120387],"iteration":902,"passed_time":0.283700501,"remaining_time":0.03047502613},
{"learn":[3.183725321],"iteration":903,"passed_time":0.283935964,"remaining_time":0.03015249176},
{"learn":[3.181264554],"iteration":904,"passed_time":0.2841698854,"remaining_time":0.02982998797},
{"learn":[3.180741589],"iteration":905,"passed_time":0.2844285155,"remaining_time":0.02951024333},
{"learn":[3.179782639],"iteration":906,"passed_time":0.2848183567,"remaining_time":0.02920408729},
{"learn":[3.176377564],"iteration":907,"passed_time":0.2851597385,"remaining_time":0.02889283694},
{"learn":[3.174078182],"iteration":908,"passed_time":0.285401535,"remaining_time":0.02857155081},
{"learn":[3.171242379],"iteration":909,"passed_time":0.285770584,"remaining_time":0.02826302479},
{"learn":[3.170421012],"iteration":910,"passed_time":0.2859906717,"remaining_time":0.02793981316},
{"learn":[3.170087224],"iteration":911,"passed_time":0.2862236764,"remaining_time":0.02761807404},
{"learn":[3.167303059],"iteration":912,"passed_time":0.2865201407,"remaining_time":0.02730257638},
{"learn":[3.16705966],"iteration":913,"passed_time":0.2868666892,"remaining_time":0.02699183291},
{"learn":[3.165667683],"iteration":914,"passed_time":0.2871004856,"remaining_time":0.02667053691},
{"learn":[3.164689733],"iteration":915,"passed_time":0.2873228234,"remaining_time":0.02634838118},
{"learn":[3.163311455],"iteration":916,"passed_time":0.2875555363,"remaining_time":0.02602738224},
{"learn":[3.159425016],"iteration":917,"passed_time":0.2878116665,"remaining_time":0.02570866737},
{"learn":[3.159327058],"iteration":918,"passed_time":0.2880435878,"remaining_time":0.02538795496},
{"learn":[3.15819426],"iteration":919,"passed_time":0.2882882593,"remaining_time":0.02506854429},
{"learn":[3.157086603],"iteration":920,"passed_time":0.2885312642,"remaining_time":0.02474915295},
{"learn":[3.153354154],"iteration":921,"passed_time":0.2887734773,"remaining_time":0.02442986034},
{"learn":[3.153261317],"iteration":922,"passed_time":0.2891579017,"remaining_time":0.02412259852},
{"learn":[3.153168454],"iteration":923,"passed_time":0.2895019919,"remaining_time":0.02381185215},
{"learn":[3.152080399],"iteration":924,"passed_time":0.2897594137,"remaining_time":0.02349400652},
{"learn":[3.151635144],"iteration":925,"passed_time":0.2900030019,"remaining_time":0.0231751859},
{"learn":[3.147762655],"iteration":926,"passed_time":0.2903383836,"remaining_time":0.02286375621},
{"learn":[3.147172317],"iteration":927,"passed_time":0.2906103474,"remaining_time":0.02254735454},
{"learn":[3.146254125],"iteration":928,"passed_time":0.2908346435,"remaining_time":0.02222740548},
{"learn":[3.144869828],"iteration":929,"passed_time":0.2910728566,"remaining_time":0.02190870964},
{"learn":[3.143466218],"iteration":930,"passed_time":0.2912979444,"remaining_time":0.02158921393},
{"learn":[3.141919643],"iteration":931,"passed_time":0.2915121987,"remaining_time":0.02126913038},
{"learn":[3.141054135],"iteration":932,"passed_time":0.2917345782,"remaining_time":0.02094985717},
{"learn":[3.139390417],"iteration":933,"passed_time":0.291962166,"remaining_time":0.02063115948},
{"learn":[3.139025283],"iteration":934,"passed_time":0.2921613367,"remaining_time":0.02031068116},
{"learn":[3.137824183],"iteration":935,"passed_time":0.2924653844,"remaining_time":0.01999763312},
{"learn":[3.135620453],"iteration":936,"passed_time":0.292828975,"remaining_time":0.01968860771},
{"learn":[3.13443178],"iteration":937,"passed_time":0.2930705632,"remaining_time":0.01937140183},
{"learn":[3.132765713],"iteration":938,"passed_time":0.2932929426,"remaining_time":0.01905310916},
{"learn":[3.131434124],"iteration":939,"passed_time":0.2935336141,"remaining_time":0.01873618813},
{"learn":[3.128384262],"iteration":940,"passed_time":0.2937685771,"remaining_time":0.01841907125},
{"learn":[3.128120455],"iteration":941,"passed_time":0.2940206655,"remaining_time":0.01810318323},
{"learn":[3.126314615],"iteration":942,"passed_time":0.2942488367,"remaining_time":0.01778598483},
{"learn":[3.125409666],"iteration":943,"passed_time":0.2944655077,"remaining_time":0.01746829283},
{"learn":[3.123072589],"iteration":944,"passed_time":0.2947021791,"remaining_time":0.01715197868},
{"learn":[3.122921099],"iteration":945,"passed_time":0.2949358505,"remaining_time":0.01683566165},
{"learn":[3.122182662],"iteration":946,"passed_time":0.2951881472,"remaining_time":0.01652056156},
{"learn":[3.120040951],"iteration":947,"passed_time":0.2954081516,"remaining_time":0.01620382266},
{"learn":[3.118767799],"iteration":948,"passed_time":0.2956294476,"remaining_time":0.01588735704},
{"learn":[3.118203218],"iteration":949,"passed_time":0.2959208701,"remaining_time":0.01557478264},
{"learn":[3.116343362],"iteration":950,"passed_time":0.2961748335,"remaining_time":0.01526032265},
{"learn":[3.11480829],"iteration":951,"passed_time":0.2964120049,"remaining_time":0.01494514311},
{"learn":[3.112607903],"iteration":952,"passed_time":0.2966455929,"remaining_time":0.01462995054},
{"learn":[3.111661241],"iteration":953,"passed_time":0.2968545554,"remaining_time":0.01431374167},
{"learn":[3.110249676],"iteration":954,"passed_time":0.2970789766,"remaining_time":0.01399848581},
{"learn":[3.107333579],"iteration":955,"passed_time":0.2972952726,"remaining_time":0.01368304602},
{"learn":[3.107149851],"iteration":956,"passed_time":0.2975097352,"remaining_time":0.01336773105},
{"learn":[3.106867336],"iteration":957,"passed_time":0.2977390731,"remaining_time":0.01305327878},
{"learn":[3.10364681],"iteration":958,"passed_time":0.2979599109,"remaining_time":0.01273864061},
{"learn":[3.102703811],"iteration":959,"passed_time":0.2982041241,"remaining_time":0.01242517184},
{"learn":[3.101469264],"iteration":960,"passed_time":0.2984297953,"remaining_time":0.01211109471},
{"learn":[3.09863569],"iteration":961,"passed_time":0.2986635916,"remaining_time":0.01179752233},
{"learn":[3.09645939],"iteration":962,"passed_time":0.2989095548,"remaining_time":0.0114845831},
{"learn":[3.096240186],"iteration":963,"passed_time":0.2991277259,"remaining_time":0.01117074495},
{"learn":[3.094838828],"iteration":964,"passed_time":0.2993621889,"remaining_time":0.01085769597},
{"learn":[3.094176802],"iteration":965,"passed_time":0.2995998186,"remaining_time":0.01054492115},
{"learn":[3.093182279],"iteration":966,"passed_time":0.2998400734,"remaining_time":0.01023239134},
{"learn":[3.090150687],"iteration":967,"passed_time":0.3000819116,"remaining_time":0.009920063193},
{"learn":[3.088612829],"iteration":968,"passed_time":0.3003589588,"remaining_time":0.009609006938},
{"learn":[3.087153684],"iteration":969,"passed_time":0.3006414228,"remaining_time":0.009298188333},
{"learn":[3.085866843],"iteration":970,"passed_time":0.3008973862,"remaining_time":0.008986636663},
{"learn":[3.082669094],"iteration":971,"passed_time":0.3011512663,"remaining_time":0.008675139358},
{"learn":[3.081047548],"iteration":972,"passed_time":0.3013875627,"remaining_time":0.008363272551},
{"learn":[3.079684322],"iteration":973,"passed_time":0.3016099838,"remaining_time":0.008051190532},
{"learn":[3.07613431],"iteration":974,"passed_time":0.30183703,"remaining_time":0.007739411025},
{"learn":[3.074005935],"iteration":975,"passed_time":0.3020509093,"remaining_time":0.007427481375},
{"learn":[3.072988853],"iteration":976,"passed_time":0.3022841223,"remaining_time":0.007116207586},
{"learn":[3.072344268],"iteration":977,"passed_time":0.3025534193,"remaining_time":0.006805905138},
{"learn":[3.070654438],"iteration":978,"passed_time":0.3027585484,"remaining_time":0.006494310027},
{"learn":[3.069724506],"iteration":979,"passed_time":0.3029945948,"remaining_time":0.006183563159},
{"learn":[3.067763166],"iteration":980,"passed_time":0.3032011822,"remaining_time":0.005872398025},
{"learn":[3.066737893],"iteration":981,"passed_time":0.303506855,"remaining_time":0.005563262108},
{"learn":[3.065248174],"iteration":982,"passed_time":0.3037382346,"remaining_time":0.005252848412},
{"learn":[3.063186837],"iteration":983,"passed_time":0.3039571557,"remaining_time":0.004942392775},
{"learn":[3.062880371],"iteration":984,"passed_time":0.3043027876,"remaining_time":0.004634052603},
{"learn":[3.061288645],"iteration":985,"passed_time":0.3046171689,"remaining_time":0.004325193067},
{"learn":[3.059970575],"iteration":986,"passed_time":0.3049649258,"remaining_time":0.004016761941},
{"learn":[3.059576341],"iteration":987,"passed_time":0.3052935157,"remaining_time":0.003708018409},
{"learn":[3.058175919],"iteration":988,"passed_time":0.3056446061,"remaining_time":0.003399485002},
{"learn":[3.056830702],"iteration":989,"passed_time":0.3059776544,"remaining_time":0.003090683378},
{"learn":[3.056336579],"iteration":990,"passed_time":0.3063097027,"remaining_time":0.002781823738},
{"learn":[3.055810414],"iteration":991,"passed_time":0.3065712496,"remaining_time":0.002472348787},
{"learn":[3.055476518],"iteration":992,"passed_time":0.3068251713,"remaining_time":0.002162916615},
{"learn":[3.053331734],"iteration":993,"passed_time":0.3070852182,"remaining_time":0.001853633108},
{"learn":[3.050890374],"iteration":994,"passed_time":0.3073241813,"remaining_time":0.001544342619},
{"learn":[3.04972623],"iteration":995,"passed_time":0.3075998534,"remaining_time":0.001235340777},
{"learn":[3.047217327],"iteration":996,"passed_time":0.3079851945,"remaining_time":0.0009267357908},
{"learn":[3.047155483],"iteration":997,"passed_time":0.3082888255,"remaining_time":0.0006178132776},
{"learn":[3.04430671],"iteration":998,"passed_time":0.3086396659,"remaining_time":0.0003089486145},
{"learn":[3.042664195],"iteration":999,"passed_time":0.3090430489,"remaining_time":0}
]}